Workbook

Sheet Consolidated Data
A1: Row ID | B1: Source (Person) | C1: Source Document | D1: Source Date | E1: Community / Company / Model | F1: Operator | G1: Location | H1: Community Type / Model | I1: Villa / Cottage Count | J1: Pricing (as reported) | K1: Monthly Fee Low ($) | L1: Monthly Fee High ($) | M1: Entry Fee? | N1: Transportation | O1: Life Enrichment / Campus Amenities | P1: Culinary / Dining | Q1: Housekeeping / Laundry & Linen | R1: Wellness / Fitness / Health | S1: Emergency / Safety / Security | T1: Maintenance (Interior / Exterior / Grounds) | U1: Utilities / Taxes / Insurance | V1: Additional / À La Carte / Concierge | W1: Residence Features (garage, W/D, patio, etc.) | X1: Notes / Flags | Y1: Sub-market / Map Reference (Lopez) | Z1: Year Opened | AA1: Tier: Transportation | AB1: Tier: Life Enrichment / Campus Amenities | AC1: Tier: Culinary / Dining | AD1: Tier: Housekeeping / Laundry & Linen | AE1: Tier: Wellness / Fitness / Health | AF1: Tier: Emergency / Safety / Security | AG1: Tier: Maintenance (Interior / Exterior / Grounds) | AH1: Tier: Utilities / Taxes / Insurance | AI1: Tier: Additional / À La Carte / Concierge
A2: 1 | B2: Laura Lopez | C2: Word doc: Villa Study Scratch List (Updated Oct 2023) | D2: Oct 2023 (doc); received by email Sept 2026 | E2: Friendship Village Kalamazoo | F2: Life Care Services | G2: Kalamazoo, MI | H2: CCRC | I2: 50 villas | J2: 2 Bed/2 Bath, 1300 sq ft: $2926; Entry Fee: $233,130 - $369,900 | 3 Bed/2 Bath, 1500 sq ft: $3346; EF: $261,530 - $415,000 | 3 Bed/2.5 bath, 1800 sq ft: $4006; EF: $304,990 - $483,900 | K2: 2926 | L2: 4006 | M2: Yes | N2: Transportation | O2: Main Campus amenities (pool; gym w/ trainer; chaplain; café; general store) | Q2: Bi-Weekly Housekeeping | R2: (via campus amenities) Main Campus amenities (pool; gym w/ trainer; chaplain; café; general store) | S2: Emergency call system | U2: All utilities, including cable | W2: In-unit washer/dryer; 1.5 car attached garage | Y2: Kalamazoo Acquisition – Fountains at Bronson Place | AA2: Included | AB2: Included | AC2: Not stated | AD2: Included | AE2: Included | AF2: Included | AG2: Not stated | AH2: Included | AI2: Not stated
A3: 2 | B3: Laura Lopez | C3: Word doc: Villa Study Scratch List (Updated Oct 2023) | D3: Oct 2023 (doc); received by email Sept 2026 | E3: Wittenberg Village | F3: Lutheran Life Communities | G3: Crown Point, IN | H3: CCRC | I3: 47 Villas | M3: CCRC (entry fee not stated) | N3: Transportation | O3: Campus amenities (chapel/chaplain; country store; fitness center | P3: One meal per day | Q3: B-weekly housekeeping & flat linen service | R3: (via campus amenities) Campus amenities (chapel/chaplain; country store; fitness center | S3: Emergency call system | U3: Basic cable & Wi-Fi | W3: Many with a garage | Y3: NW Indiana | Z3: 1974 | AA3: Included | AB3: Included | AC3: Included | AD3: Included | AE3: Included | AF3: Included | AG3: Not stated | AH3: Included | AI3: Not stated
A4: 3 | B4: Laura Lopez | C4: Word doc: Villa Study Scratch List (Updated Oct 2023) | D4: Oct 2023 (doc); received by email Sept 2026 | E4: The Moorings of Arlington Heights | F4: Presbyterian Homes | G4: Arlington Heights, IL | H4: CCRC | I4: 72 Villas (1276 – 2036 sq ft) | J4: $4620 for a villa; Entrance Fee: $299,600 | K4: 4620 | L4: 4620 | M4: Yes | N4: Transportation | O4: Campus amenities (pool; fitness center) | Q4: Weekly Housekeeping | R4: (via campus amenities) Campus amenities (pool; fitness center) | S4: Emergency call system | V4: $490 per month “discretionary dollar account” | W4: Attached two-car garage; In-unit washer/dryer; Some include basements | Y4: NW Chicago New Dev – Schaumburg add Comps | Z4: 1989 | AA4: Included | AB4: Included | AC4: Not stated | AD4: Included | AE4: Included | AF4: Included | AG4: Not stated | AH4: Not stated | AI4: Included
A5: 4 | B5: Laura Lopez | C5: Word doc: Villa Study Scratch List (Updated Oct 2023) | D5: Oct 2023 (doc); received by email Sept 2026 | E5: Newcastle Place | F5: Life Care Services, LLC | G5: Mequon, WI | H5: CCRC | I5: 29 Villas (1718 – 1982 sq ft) | M5: CCRC (entry fee not stated) | Q5: Bi-weekly housekeeping & linen service | U5: All utilities including cable & Wi-Fi | W5: Attached two-car garage; 2 Bed/2 Bath; In-unit washer/dryer | Y5: Wright House, Mequon WI | Z5: 2003 | AA5: Not stated | AB5: Not stated | AC5: Not stated | AD5: Included | AE5: Not stated | AF5: Not stated | AG5: Not stated | AH5: Included | AI5: Not stated
A6: 5 | B6: Laura Lopez | C6: Word doc: Villa Study Scratch List (Updated Oct 2023) | D6: Oct 2023 (doc); received by email Sept 2026 | E6: Crown Point Christian Village | F6: Christian Homes, Inc. | G6: Crown Point, IN | H6: Villa, AL, MC | I6: 20 Villas (up to 1614 sq ft) | M6: Not stated | P6: Weekly continental breakfast | Q6: Bi-weekly housekeeping | U6: Paid utilities including basic cable & Wi-Fi | W6: 2 Bed/2 Bath; In-unit washer/dryer; Attached one-car garage | Y6: NW Indiana | Z6: 1993 | AA6: Not stated | AB6: Not stated | AC6: Included | AD6: Included | AE6: Not stated | AF6: Not stated | AG6: Not stated | AH6: Included | AI6: Not stated
A7: 6 | B7: Laura Lopez | C7: Word doc: Villa Study Scratch List (Updated Oct 2023) | D7: Oct 2023 (doc); received by email Sept 2026 | E7: Friendship Village of Schaumburg | F7: Friendship Senior Options | G7: Schaumburg, IL | H7: CCRC | I7: 28 Villas (1350 – 1750 sq ft) | M7: CCRC (entry fee not stated) | W7: Attached garage; In-unit washer/dryer w/ laundry room | Y7: NW Chicago New Dev – Schaumburg add Comps | Z7: 1977 | AA7: Not stated | AB7: Not stated | AC7: Not stated | AD7: Not stated | AE7: Not stated | AF7: Not stated | AG7: Not stated | AH7: Not stated | AI7: Not stated
A8: 7 | B8: Laura Lopez | C8: Word doc: Villa Study Scratch List (Updated Oct 2023) | D8: Oct 2023 (doc); received by email Sept 2026 | E8: Sunrise of Olympia Fields | F8: Sunrise Senior Living | G8: Olympia Fields, IL | H8: Villa, IL, AL | I8: 32 Villas | M8: Not stated | Y8: Frankfort, IL (New Dev) | Z8: 1999 | AA8: Not stated | AB8: Not stated | AC8: Not stated | AD8: Not stated | AE8: Not stated | AF8: Not stated | AG8: Not stated | AH8: Not stated | AI8: Not stated
A9: 8 | B9: Laura Lopez | C9: Word doc: Villa Study Scratch List (Updated Oct 2023) | D9: Oct 2023 (doc); received by email Sept 2026 | E9: Smith Crossing | F9: Smith Senior Living Communities | G9: Orland Park, IL | H9: CCRC | I9: 10 Villas (1506 – 1809 sq ft) | M9: CCRC (entry fee not stated) | O9: Campus amenities (fitness center w/ exercise physiologist; movie theater; etc.) | R9: (via campus amenities) Campus amenities (fitness center w/ exercise physiologist; movie theater; etc.) | W9: Attached two-car garage; In-unit washer/dryer; Enclosed porch or screened patio | Y9: Frankfort, IL (New Dev) | Z9: 2004 | AA9: Not stated | AB9: Included | AC9: Not stated | AD9: Not stated | AE9: Included | AF9: Not stated | AG9: Not stated | AH9: Not stated | AI9: Not stated
A10: 9 | B10: Laura Lopez | C10: Word doc: Villa Study Scratch List (Updated Oct 2023) | D10: Oct 2023 (doc); received by email Sept 2026 | E10: Briar Creek Independent Senior Living Community | F10: Warmus Senior Living | G10: Uniontown, OH | H10: Villa & IL | I10: 36 Villas | M10: Not stated | O10: Campus amenities (gym, movie theater, coffee bar, etc.) | Q10: Housekeeping | R10: (via campus amenities) Campus amenities (gym, movie theater, coffee bar, etc.) | T10: Maintenance | Y10: Lancaster-Jackson Twp OH Danbury New Devs (Jackson) | Z10: 2017 | AA10: Not stated | AB10: Included | AC10: Not stated | AD10: Included | AE10: Included | AF10: Not stated | AG10: Included | AH10: Not stated | AI10: Not stated
A11: 10 | B11: Laura Lopez | C11: Word doc: Villa Study Scratch List (Updated Oct 2023) | D11: Oct 2023 (doc); received by email Sept 2026 | E11: Primrose Retirement Community of Lancaster | F11: Primrose Retirement Communities | G11: Lancaster, OH | H11: Villa, IL, AL & MC | I11: 10 Villas (1594 sq ft) | M11: Not stated | O11: Campus amenities (chapel, wellness center, ice cream parlor) | P11: Daily meal | R11: (via campus amenities) Campus amenities (chapel, wellness center, ice cream parlor) | S11: Emergency call system; Emergency call system | U11: All utilities including cable and internet | W11: Attached garage; In-unit washer/dryer | Y11: Lancaster-Jackson Twp OH Danbury New Devs (Lancaster) | Z11: 2007 | AA11: Not stated | AB11: Included | AC11: Included | AD11: Not stated | AE11: Included | AF11: Included | AG11: Not stated | AH11: Included | AI11: Not stated
A12: 11 | B12: Laura Lopez | C12: Word doc: Villa Study Scratch List (Updated Oct 2023) | D12: Oct 2023 (doc); received by email Sept 2026 | E12: Concordia Village | F12: Lutheran Senior Services | G12: Springfield, IL | H12: CCRC | I12: 23 Villas (1895 sq ft) | M12: CCRC (entry fee not stated) | N12: Transportation services | O12: Campus amenities (Chapel w/ chaplain; art studio; village market; fitness center w/ indoor pool; movie theater) | Q12: Scheduled housekeeping services | R12: (via campus amenities) Campus amenities (Chapel w/ chaplain; art studio; village market; fitness center w/ indoor pool; movie theater) | U12: “Many utility costs included” | W12: 3 Bed/2 Bath; In-unit washer/dryer; Optional patio; Attached two-car garage | Y12: Illinois Holiday Acquisitions (Springfield) | Z12: 1995 | AA12: Included | AB12: Included | AC12: Not stated | AD12: Included | AE12: Included | AF12: Not stated | AG12: Not stated | AH12: Included | AI12: Not stated
A13: 12 | B13: Laura Lopez | C13: Word doc: Villa Study Scratch List (Updated Oct 2023) | D13: Oct 2023 (doc); received by email Sept 2026 | E13: Lewis Memorial Christian Village | F13: Christian Horizons | G13: Springfield, IL | H13: CCRC | I13: 20 villas | M13: CCRC (entry fee not stated) | O13: Campus amenities (bistro; chapel w/ pastor; fitness center w/ pool) | Q13: Bi-weekly housekeeping | R13: (via campus amenities) Campus amenities (bistro; chapel w/ pastor; fitness center w/ pool) | S13: Emergency response system | U13: “Paid basic cable, sewer, water and trash” | W13: “One- to two-bed, and up to two-bath townhomes”; In-unit washer/dryer; Attached garages; Private patios | Y13: Illinois Holiday Acquisitions (Springfield) | AA13: Not stated | AB13: Included | AC13: Not stated | AD13: Included | AE13: Included | AF13: Included | AG13: Not stated | AH13: Included | AI13: Not stated
A14: 13 | B14: Laura Lopez | C14: Word doc: Villa Study Scratch List (Updated Oct 2023) | D14: Oct 2023 (doc); received by email Sept 2026 | E14: Good Samaritan Home of Quincy | F14: Good Samaritan Home | G14: Quincy, IL | H14: CCRC | I14: 180 villas | M14: CCRC (entry fee not stated) | O14: Campus Amenities (gym w/ pool; chapel; buffet-style meals for add. Fee; general store) | R14: (via campus amenities) Campus Amenities (gym w/ pool; chapel; buffet-style meals for add. Fee; general store) | U14: All utilities except phone, internet, cable, and garbage stickers | W14: One and two bedroom cottages | Y14: Illinois Holiday Acquisitions (Quincy) | Z14: 1957 | AA14: Not stated | AB14: Available (extra cost) | AC14: Not stated | AD14: Not stated | AE14: Available (extra cost) | AF14: Not stated | AG14: Not stated | AH14: Included | AI14: Not stated
A15: 14 | B15: Laura Lopez | C15: Word doc: Villa Study Scratch List (Updated Oct 2023) | D15: Oct 2023 (doc); received by email Sept 2026 | E15: Provision Living at East Lansing | F15: Provision Senior Living Communities | G15: East Lansing, MI | H15: Villa, AL & MC | I15: 22 villas | M15: Not stated | Q15: Housekeeping and maintenance services | T15: Housekeeping and maintenance services | V15: Concierge services | W15: 2 Bed/2 Bath | Y15: Michigan Holiday Acquisitions (Lansing) | Z15: 2022 | AA15: Not stated | AB15: Not stated | AC15: Not stated | AD15: Included | AE15: Not stated | AF15: Not stated | AG15: Included | AH15: Not stated | AI15: Included
A16: 15 | B16: Laura Lopez | C16: Word doc: Villa Study Scratch List (Updated Oct 2023) | D16: Oct 2023 (doc); received by email Sept 2026 | E16: American House Village of Rochester Hills | F16: American House Senior Living | G16: Rochester Hills, MI | H16: rental-only continuum | I16: 12 villas (1020 – 1280 sq ft) | M16: Not stated | N16: Transportation | O16: Campus amenities (ice cream parlor; library; fitness center) | Q16: Housekeeping and laundry services | R16: (via campus amenities) Campus amenities (ice cream parlor; library; fitness center) | W16: 2-3 Bed/2 Bath; In-unit washer/dryer | Y16: Michigan Holiday Acquisitions (Waterford/Metro Detroit) | Z16: 2017 | AA16: Included | AB16: Included | AC16: Not stated | AD16: Included | AE16: Included | AF16: Not stated | AG16: Not stated | AH16: Not stated | AI16: Not stated
A17: 16 | B17: Laura Lopez | C17: Word doc: Villa Study Scratch List (Updated Oct 2023) | D17: Oct 2023 (doc); received by email Sept 2026 | E17: The Villas at Westlake | F17: Trilogy Health Services | G17: Commerce Charter Twp, MI | H17: Villa, AL, MC & SNF | I17: 34 villas | J17: 2 Bed/2 Bath: $3624 | K17: 3624 | L17: 3624 | M17: Not stated | Q17: Bi-weekly housekeeping | U17: Cable included; Electric, heat, and water included | W17: Attached garage; Private patio; Washer/dryer hookups | Y17: Michigan Holiday Acquisitions (Waterford/Metro Detroit) | Z17: 2011 | AA17: Not stated | AB17: Not stated | AC17: Not stated | AD17: Included | AE17: Not stated | AF17: Not stated | AG17: Not stated | AH17: Included | AI17: Not stated
A18: 17 | B18: Laura Lopez | C18: Word doc: Villa Study Scratch List (Updated Oct 2023) | D18: Oct 2023 (doc); received by email Sept 2026 | E18: Vitalia Senior Residences at Strongsville | F18: Arrow Senior Living | G18: Strongsville, OH | H18: Villa, AL & MC | I18: 71 Villas (1191 – 1383 sq ft) | M18: Not stated | O18: Campus amenities (wellness center; library; demonstration kitchen) | R18: (via campus amenities) Campus amenities (wellness center; library; demonstration kitchen) | W18: Attached garage; 2-3 Bed/ 2 Bath | X18: Confirm additional amenities/that it’s on par with our proposed villa product | Y18: Ohio Holiday Acquisitions (Strongsville/Cleveland) | Z18: 2024? | AA18: Not stated | AB18: Included | AC18: Not stated | AD18: Not stated | AE18: Included | AF18: Not stated | AG18: Not stated | AH18: Not stated | AI18: Not stated
A19: 18 | B19: Laura Lopez | C19: Word doc: Villa Study Scratch List (Updated Oct 2023) | D19: Oct 2023 (doc); received by email Sept 2026 | E19: Samaritas Senior Living of Grand Rapids | F19: Samaritas Senior Living | G19: Grand Rapids, MI | H19: rental-only continuum | I19: 25 Villas | J19: 1 Bedroom: $3125 | 2 Bedroom: $3645 | Stand Alone: $4045 | K19: 3125 | L19: 4045 | M19: Not stated | Y19: Michigan Holiday Acquisitions (Wyoming/Grand Rapids) | Z19: 1978 | AA19: Not stated | AB19: Not stated | AC19: Not stated | AD19: Not stated | AE19: Not stated | AF19: Not stated | AG19: Not stated | AH19: Not stated | AI19: Not stated
A20: 19 | B20: Laura Lopez | C20: Word doc: Villa Study Scratch List (Updated Oct 2023) | D20: Oct 2023 (doc); received by email Sept 2026 | E20: Legacies Village | F20: WRG Senior Living/Legacies | G20: Caledonia, MI | H20: IL | I20: 20 Villas (1200 sq ft) | M20: Not stated | P20: Daily continental breakfast in community center | U20: Utilities, including Cable & Internet | W20: 1 Bed / 1.5 Bath; In-unit washer/dryer; Attached 1-car garage; Private patio | Y20: Michigan Holiday Acquisitions (Wyoming/Grand Rapids) | Z20: 2022 | AA20: Not stated | AB20: Not stated | AC20: Included | AD20: Not stated | AE20: Not stated | AF20: Not stated | AG20: Not stated | AH20: Included | AI20: Not stated
A21: 20 | B21: Laura Lopez | C21: Word doc: Villa Study Scratch List (Updated Oct 2023) | D21: Oct 2023 (doc); received by email Sept 2026 | E21: Holiday Aurora Pond | F21: Holiday Senior Living/Atria | G21: Wyoming, MI | H21: IL | I21: 18 villas (1252 – 1474 sq ft) | J21: $4149 starting rate | K21: 4149 | L21: 4149 | M21: Not stated | O21: Campus amenities (billiards; fitness room; chapel) | R21: (via campus amenities) Campus amenities (billiards; fitness room; chapel) | U21: Cable included | W21: In-unit washer/dryer; Patio; Some w/ attached garage | Y21: Michigan Holiday Acquisitions (Wyoming/Grand Rapids) | AA21: Not stated | AB21: Included | AC21: Not stated | AD21: Not stated | AE21: Included | AF21: Not stated | AG21: Not stated | AH21: Included | AI21: Not stated
A22: 21 | B22: Laura Lopez | C22: Word doc: Villa Study Scratch List (Updated Oct 2023) | D22: Oct 2023 (doc); received by email Sept 2026 | E22: Holland Home Raybrook Campus | F22: Holland Home | G22: Grand Rapids, MI | H22: CCRC | I22: 42 Villas | M22: CCRC (entry fee not stated) | O22: Campus Amenities (billiards; wellness center; pool; library) | P22: Daily meal delivery available | R22: (via campus amenities) Campus Amenities (billiards; wellness center; pool; library) | W22: 2 Bed/2 Bath; In-unit washer/dryer; Attached garage; Patio | Y22: Michigan Holiday Acquisitions (Wyoming/Grand Rapids) | Z22: 1998 (Raybrook Homes opens); facility first established 1983 | AA22: Not stated | AB22: Included | AC22: Available (extra cost) | AD22: Not stated | AE22: Included | AF22: Not stated | AG22: Not stated | AH22: Not stated | AI22: Not stated
A23: 22 | B23: Laura Lopez | C23: Word doc: Villa Study Scratch List (Updated Oct 2023) | D23: Oct 2023 (doc); received by email Sept 2026 | E23: Breton Woods of Holland Homes | F23: Holland Home | G23: Grand Rapids, MI | H23: CCRC | I23: 126 Villas | M23: CCRC (entry fee not stated) | O23: Campus Amenities (wellness center; pool; gym; art studio; woodshop; chapel; billiards) | R23: (via campus amenities) Campus Amenities (wellness center; pool; gym; art studio; woodshop; chapel; billiards) | W23: Attached garage; In-unit washer/dryer; 2-3 Bedroom / 2-3 Bath | Y23: Michigan Holiday Acquisitions (Wyoming/Grand Rapids) | Z23: 1999 | AA23: Not stated | AB23: Included | AC23: Not stated | AD23: Not stated | AE23: Included | AF23: Not stated | AG23: Not stated | AH23: Not stated | AI23: Not stated
A24: 23 | B24: Laura Lopez | C24: Word doc: Villa Study Scratch List (Updated Oct 2023) | D24: Oct 2023 (doc); received by email Sept 2026 | E24: Waterford Place | F24: Sunset Senior Communities | G24: Jenison, MI | H24: CCRC | I24: 20 Villas (767 – 1225 sq ft) | M24: CCRC (entry fee not stated) | O24: Campus amenities (fitness/aquatics center; health clinic; library; woodshop; bistro) | R24: (via campus amenities) Campus amenities (fitness/aquatics center; health clinic; library; woodshop; bistro) | S24: Emergency response system | W24: In-unit washer/dryer; Attached two-car garage; Porch | Y24: Michigan Holiday Acquisitions (Wyoming/Grand Rapids) | Z24: 2023? | AA24: Not stated | AB24: Included | AC24: Not stated | AD24: Not stated | AE24: Included | AF24: Included | AG24: Not stated | AH24: Not stated | AI24: Not stated
A25: 24 | B25: Laura Lopez | C25: Word doc: Villa Study Scratch List (Updated Oct 2023) | D25: Oct 2023 (doc); received by email Sept 2026 | E25: Holiday Wescourt | F25: Holiday Senior Living/Atria | G25: Saginaw, MI | H25: IL | I25: 8 villas (1298 sq ft) | J25: $5219 starting rate | K25: 5219 | L25: 5219 | M25: Not stated | O25: Campus amenities (billiards; fitness room; chapel) | R25: (via campus amenities) Campus amenities (billiards; fitness room; chapel) | U25: Cable included | W25: Patio | Y25: Michigan Holiday Acquisitions (Wyoming/Grand Rapids) | AA25: Not stated | AB25: Included | AC25: Not stated | AD25: Not stated | AE25: Included | AF25: Not stated | AG25: Not stated | AH25: Included | AI25: Not stated
A26: 25 | B26: Laura Lopez | C26: Word doc: Villa Study Scratch List (Updated Oct 2023) | D26: Oct 2023 (doc); received by email Sept 2026 | E26: Vitalia North Royalton | F26: Arrow Senior Living | G26: North Royalton, OH | H26: rental-only continuum | I26: 16 villas | M26: Not stated | O26: Campus amenities (wellness center; library; demonstration kitchen) | R26: (via campus amenities) Campus amenities (wellness center; library; demonstration kitchen) | W26: Attached garage; 2-3 Bed/ 2 Bath | X26: Confirm additional amenities/that it’s on par with our proposed villa product | Y26: Ohio Holiday Acquisitions (Strongsville/Cleveland) | Z26: 2022 | AA26: Not stated | AB26: Included | AC26: Not stated | AD26: Not stated | AE26: Included | AF26: Not stated | AG26: Not stated | AH26: Not stated | AI26: Not stated
A27: 26 | B27: Laura Lopez | C27: Word doc: Villa Study Scratch List (Updated Oct 2023) | D27: Oct 2023 (doc); received by email Sept 2026 | E27: Western Reserve Masonic Community | F27: Ohio Masonic Communities | G27: Medina, OH | H27: CCRC | I27: 19 villas (1100 – 1699 sq ft) | M27: CCRC (entry fee not stated) | O27: Campus amenities (wood shop; computer lab; wellness center) | P27: 3 meals provided daily | R27: (via campus amenities) Campus amenities (wood shop; computer lab; wellness center) | U27: Water and sewer included; Wi-Fi and basic cable included | W27: 2 Bed/2 Bath | Y27: Ohio Holiday Acquisitions (Strongsville/Cleveland) | Z27: 1998 | AA27: Not stated | AB27: Included | AC27: Included | AD27: Not stated | AE27: Included | AF27: Not stated | AG27: Not stated | AH27: Included | AI27: Not stated
A28: 27 | B28: Laura Lopez | C28: Word doc: Villa Study Scratch List (Updated Oct 2023) | D28: Oct 2023 (doc); received by email Sept 2026 | E28: Provision Living at West Clermont | F28: Provision Living Senior Communities | G28: Batavia, OH | H28: Villa, AL & MC | I28: 15 villa | M28: Not stated | Q28: Housekeeping and maintenance services | T28: Housekeeping and maintenance services | V28: Concierge | W28: 2 Bed/2 Bath | Y28: Ohio Holiday Acquisitions (Cincinnati) | Z28: 2021 | AA28: Not stated | AB28: Not stated | AC28: Not stated | AD28: Included | AE28: Not stated | AF28: Not stated | AG28: Included | AH28: Not stated | AI28: Included
A29: 28 | B29: Laura Lopez | C29: Word doc: Villa Study Scratch List (Updated Oct 2023) | D29: Oct 2023 (doc); received by email Sept 2026 | E29: Solarbron | F29: CarDon & Associates | G29: Evansville, IN | H29: rental-only continuum | I29: 9 villa | M29: Not stated | O29: Campus amenities (shuffleboard courts; billiards/games room; fitness center; business center; private fishing lake; vegetable/flower gardens) | R29: (via campus amenities) Campus amenities (shuffleboard courts; billiards/games room; fitness center; business center; private fishing lake; vegetable/flower gardens) | S29: Emergency alert system | U29: Basic cable, water, sewer, and trash removal | W29: 2-3 Bed/2 Bath; Attached double garage; Laundry room with washer/dryer hookups | Y29: Indiana Holiday Acquisitions (Evansville) | AA29: Not stated | AB29: Included | AC29: Not stated | AD29: Not stated | AE29: Included | AF29: Included | AG29: Not stated | AH29: Included | AI29: Not stated
A30: 29 | B30: Laura Lopez | C30: Word doc: Villa Study Scratch List (Updated Oct 2023) | D30: Oct 2023 (doc); received by email Sept 2026 | E30: The Village at Hamilton Pointe | F30: TLC Management | G30: Newburgh, IN | H30: rental-only continuum | I30: 24 villas | M30: Not stated | N30: Transportation | O30: Gardens; Campus amenities (movie theater; salon/spa; therapy gym) | P30: “Deliciously prepared chef inspired meals” (doesn’t specify which or how many daily) | R30: (via campus amenities) Campus amenities (movie theater; salon/spa; therapy gym) | U30: Paid utilities | W30: One- and two-bedroom cottages – 1 bath; Washers/dryers (two-bedroom layouts only); Porches | Y30: Indiana Holiday Acquisitions (Evansville) | Z30: 2013 | AA30: Included | AB30: Included | AC30: Included | AD30: Not stated | AE30: Included | AF30: Not stated | AG30: Not stated | AH30: Included | AI30: Not stated
A31: 30 | B31: Laura Lopez | C31: Word doc: Villa Study Scratch List (Updated Oct 2023) | D31: Oct 2023 (doc); received by email Sept 2026 | E31: Athens Crossing at Four Seasons | F31: BHI Senior Living | G31: Columbus, IN | H31: CCRC | I31: 12 villas (1850 – 2400 sq ft) | M31: CCRC (entry fee not stated) | O31: Campus amenities (indoor pool; fitness center; dog park; rehab center) | R31: (via campus amenities) Campus amenities (indoor pool; fitness center; dog park; rehab center) | U31: Utilities included (excluding cable, phone, and internet) | W31: 2 Bed/2 Bath; In-unit washer/dryer; Fireplace; Patio or covered porch; Island kitchen counter; Attached two-car garage | Y31: Indiana Holiday Acquisitions (Columbus/Indianapolis) | Z31: 2023? | AA31: Not stated | AB31: Included | AC31: Not stated | AD31: Not stated | AE31: Included | AF31: Not stated | AG31: Not stated | AH31: Included | AI31: Not stated
A32: 31 | B32: Laura Lopez | C32: Word doc: Villa Study Scratch List (Updated Oct 2023) | D32: Oct 2023 (doc); received by email Sept 2026 | E32: Traditions of Columbus | F32: Traditions Management | G32: Columbus, IN | H32: rental-only continuum | I32: 30 villas (1481 – 1530 sq ft) | M32: Not stated | O32: Campus amenities (pub; chapel; movie theater; fitness center; salon) | R32: (via campus amenities) Campus amenities (pub; chapel; movie theater; fitness center; salon) | S32: Gated security; Emergency response system | U32: All utilities, including cable & internet | W32: 2 Bed/2 Bath; Attached single-car garage; In-unit washer/dryer; Covered porch/patio | Y32: Indiana Holiday Acquisitions (Columbus/Indianapolis) | Z32: 2021 | AA32: Not stated | AB32: Included | AC32: Not stated | AD32: Not stated | AE32: Included | AF32: Included | AG32: Not stated | AH32: Included | AI32: Not stated
A33: 32 | B33: Laura Lopez | C33: Word doc: Villa Study Scratch List (Updated Oct 2023) | D33: Oct 2023 (doc); received by email Sept 2026 | E33: The Heritage at Brentwood | F33: Life Care Services LLC | G33: Brentwood, TN | H33: CCRC | I33: 65 villas (1803 – 2171 sq ft) | M33: CCRC (entry fee not stated) | N33: Transportation | O33: Campus amenities (multiple dining venues; putting green; bocce court; woodworking shop; art studio; greenhouse/gardening area; market; medical clinic; bank services) | R33: (via campus amenities) Campus amenities (multiple dining venues; putting green; bocce court; woodworking shop; art studio; greenhouse/gardening area; market; medical clinic; bank services) | U33: Cable TV and Wi-Fi | W33: 2-3 Bed/2-3 Bath; Attached garage; In-unit washer/dryer | Y33: Tennessee Holiday Acquisitions (Franklin) | Z33: 2009 | AA33: Included | AB33: Included | AC33: Not stated | AD33: Not stated | AE33: Included | AF33: Not stated | AG33: Not stated | AH33: Included | AI33: Not stated
A34: 33 | B34: Laura Lopez | C34: Word doc: Villa Study Scratch List (Updated Oct 2023) | D34: Oct 2023 (doc); received by email Sept 2026 | E34: Holiday Mallard Point | F34: Holiday/Atria | G34: Cedar Falls, IA | H34: IL | I34: 8 villas (743 sq ft) | J34: $3239 | K34: 3239 | L34: 3239 | M34: Not stated | O34: Campus amenities (billiards; fitness room; salon) | R34: (via campus amenities) Campus amenities (billiards; fitness room; salon) | Y34: Iowa Holiday Acquisitions (Cedar Falls) | AA34: Not stated | AB34: Included | AC34: Not stated | AD34: Not stated | AE34: Included | AF34: Not stated | AG34: Not stated | AH34: Not stated | AI34: Not stated
A35: 34 | B35: Laura Lopez | C35: Word doc: Villa Study Scratch List (Updated Oct 2023) | D35: Oct 2023 (doc); received by email Sept 2026 | E35: Windcrest | F35: Western Home Communities | G35: Cedar Falls, IA | H35: CCRC | I35: 174 villas (1150 – 1450 sq ft) | M35: CCRC (entry fee not stated) | O35: Campus amenities (pub; salon; wellness/aquatic center; chapel; therapy; market; fine dining) | R35: (via campus amenities) Campus amenities (pub; salon; wellness/aquatic center; chapel; therapy; market; fine dining) | T35: Lawn Care and Mowing; Snow Removal; Service requests | Y35: Iowa Holiday Acquisitions (Cedar Falls) | Z35: 2000 | AA35: Not stated | AB35: Included | AC35: Not stated | AD35: Not stated | AE35: Included | AF35: Not stated | AG35: Included | AH35: Not stated | AI35: Not stated
A36: 35 | B36: Laura Lopez | C36: Word doc: Villa Study Scratch List (Updated Oct 2023) | D36: Oct 2023 (doc); received by email Sept 2026 | E36: Friendship Village | F36: Friendship Village | G36: Waterloo, IA | H36: CCRC | I36: 8 villas | M36: CCRC (entry fee not stated) | O36: Campus amenities (chapel w/ chaplain; billiards; woodshop; media center; library; bistro) | P36: Included meals | Q36: Housekeeping services | W36: Attached two-car garage | Y36: Iowa Holiday Acquisitions (Cedar Falls) | AA36: Not stated | AB36: Included | AC36: Included | AD36: Included | AE36: Not stated | AF36: Not stated | AG36: Not stated | AH36: Not stated | AI36: Not stated
A37: 36 | B37: Laura Lopez | C37: Word doc: Villa Study Scratch List (Updated Oct 2023) | D37: Oct 2023 (doc); received by email Sept 2026 | E37: Landmark Commons | F37: Friendship Village | G37: Waterloo, IA | H37: IL | I37: 15 villas | M37: Not stated | O37: Campus amenities (bistro; craft room; woodshop; billiards; wellness center w/ pool) | P37: Continental breakfast | Q37: Weekly housekeeping | R37: (via campus amenities) Campus amenities (bistro; craft room; woodshop; billiards; wellness center w/ pool) | U37: Utilities, including Cable, Internet & Phone | W37: Attached two-car garage | Y37: Iowa Holiday Acquisitions (Cedar Falls) | AA37: Not stated | AB37: Included | AC37: Included | AD37: Included | AE37: Included | AF37: Not stated | AG37: Not stated | AH37: Included | AI37: Not stated
A38: 37 | B38: Laura Lopez | C38: Word doc: Villa Study Scratch List (Updated Oct 2023) | D38: Oct 2023 (doc); received by email Sept 2026 | E38: NewAldaya Lifescapes | F38: NewAldaya | G38: Cedar Falls, IA | H38: CCRC | I38: 14 villas (Park Ridge Ranches; 650 – 1300 sq ft) | M38: CCRC (entry fee not stated) | O38: Campus amenities (general store; spa; pub; wellness center; chapel; café) | R38: (via campus amenities) Campus amenities (general store; spa; pub; wellness center; chapel; café) | W38: In-unit washer/dryer; Some w/ attached garages; Private patio | Y38: Iowa Holiday Acquisitions (Cedar Falls) | AA38: Not stated | AB38: Included | AC38: Not stated | AD38: Not stated | AE38: Included | AF38: Not stated | AG38: Not stated | AH38: Not stated | AI38: Not stated
A39: 38 | B39: Laura Lopez | C39: Word doc: Villa Study Scratch List (Updated Oct 2023) | D39: Oct 2023 (doc); received by email Sept 2026 | E39: Brio of Johnston | F39: Wesley Life, Inc. | G39: Johnston, IA | H39: CCRC | I39: 19 villas | M39: CCRC (entry fee not stated) | O39: Campus amenities:; Library; Salon; Chapel; General Store; Onsite banking; Bistro | R39: Wellness/fitness center | Y39: Iowa Holiday Acquisitions (Des Moines) | Z39: 2018 | AA39: Not stated | AB39: Included | AC39: Not stated | AD39: Not stated | AE39: Included | AF39: Not stated | AG39: Not stated | AH39: Not stated | AI39: Not stated
A40: 39 | B40: Laura Lopez | C40: Word doc: Villa Study Scratch List (Updated Oct 2023) | D40: Oct 2023 (doc); received by email Sept 2026 | E40: Deerfield Retirement Community | F40: Immanuel Communities | G40: Urbandale, IA | H40: CCRC | I40: 18 villas (1920+ sq ft) | M40: CCRC (entry fee not stated) | N40: Transportation | O40: Campus amenities (bistro; convenience store; woodworking shop; game room; fishing dock/pond; cocktail lounge; access to walking/biking trails) | U40: Paid utilities, including cable | W40: Attached two-car garage; Private patio | Y40: Iowa Holiday Acquisitions (Des Moines) | Z40: 2005 | AA40: Included | AB40: Included | AC40: Not stated | AD40: Not stated | AE40: Not stated | AF40: Not stated | AG40: Not stated | AH40: Included | AI40: Not stated
A41: 40 | B41: Laura Lopez | C41: Word doc: Villa Study Scratch List (Updated Oct 2023) | D41: Oct 2023 (doc); received by email Sept 2026 | E41: Valley View Village | F41: Cassia – An Augustana/Elim Affiliation | G41: Des Moines, IA | H41: rental-only continuum | I41: 36 villas (600 – 1200 sq ft) | J41: $300 extra for units w/ a washer/dryer | $804 for a one-bedroom cottage apartment | $1282 – 1823 for a two-bedroom apartment | K41: 804 | L41: 1823 | M41: Not stated | O41: Community amenities (café; salon; library; rehab) | R41: (via campus amenities) Community amenities (café; salon; library; rehab) | U41: All utilities/taxes included except phone and cable | W41: Many w/ in-unit washer/dryer; Reserved parking space | Y41: Iowa Holiday Acquisitions (Des Moines) | Z41: 1962 | AA41: Not stated | AB41: Included | AC41: Not stated | AD41: Not stated | AE41: Included | AF41: Not stated | AG41: Not stated | AH41: Included | AI41: Not stated
A42: 41 | B42: Laura Lopez | C42: Word doc: Villa Study Scratch List (Updated Oct 2023) | D42: Oct 2023 (doc); received by email Sept 2026 | E42: Attic Angel Community | F42: Attic Angel Community | G42: Middleton, WI | H42: CCRC | I42: 123 villas (1375 – 2300 sq ft) | M42: CCRC (entry fee not stated) | O42: Community amenities (fitness room; art studio; library; computer lab; café) | P42: Meal plans/housekeeping/laundry extra | Q42: Meal plans/housekeeping/laundry extra | R42: (via campus amenities) Community amenities (fitness room; art studio; library; computer lab; café) | S42: Optional daily check-in service | T42: Exterior/interior maintenance | U42: Utilities/cable/internet/municipal fees extra | W42: Attached 1- and 2-car garage | Y42: Madison, WI – October 2022 | Z42: 2004 | AA42: Not stated | AB42: Included | AC42: Available (extra cost) | AD42: Available (extra cost) | AE42: Included | AF42: Available (extra cost) | AG42: Included | AH42: Available (extra cost) | AI42: Not stated
A43: 42 | B43: Laura Lopez | C43: Word doc: Villa Study Scratch List (Updated Oct 2023) | D43: Oct 2023 (doc); received by email Sept 2026 | E43: Waunakee Valley Senior Living | F43: Trilogy Health Services, LLC | G43: Waunakee, WI | H43: rental-only continuum | I43: 8 villas | J43: $3025 for a one bedroom villa | K43: 3025 | L43: 3025 | M43: Not stated | O43: Campus amenities (fitness center; café; salon) | Q43: Bi-monthly “interior cleaning services” | R43: (via campus amenities) Campus amenities (fitness center; café; salon) | T43: 24 hour emergency maintenance | U43: Cable included | W43: Attached garage; Private patio; Washer and dryer | Y43: Madison, WI – October 2022 | Z43: 1974 | AA43: Not stated | AB43: Included | AC43: Not stated | AD43: Included | AE43: Included | AF43: Not stated | AG43: Included | AH43: Included | AI43: Not stated
A44: 43 | B44: Laura Lopez | C44: Word doc: Villa Study Scratch List (Updated Oct 2023) | D44: Oct 2023 (doc); received by email Sept 2026 | E44: Laurel Lake | F44: Laurel Lake Retirement Community | G44: Hudson, OH | H44: CCRC | I44: 66 villas (1500 – 2025 sq ft) | M44: CCRC (entry fee not stated) | N44: Transportation services | O44: Campus amenities (pub; grille; convenience/gift shop; library/DVD center; chapels; greenhouse; woodworking/hobby shop; indoor pool & therapy spa; wellness center); Nature Trails; Stocked fishing lakes; Par 3 golf course; Community garden | Q44: Bi-weekly housekeeping; weekly linen service | R44: (via campus amenities) Campus amenities (pub; grille; convenience/gift shop; library/DVD center; chapels; greenhouse; woodworking/hobby shop; indoor pool & therapy spa; wellness center) | S44: Wireless emergency call system | U44: All utilities included except phone; Basic cable | W44: Attached 1- and 2-car garage; In-unit washer/dryer; Private patio | Y44: American House Macedonia (Cleveland) | Z44: 1989 | AA44: Included | AB44: Included | AC44: Not stated | AD44: Included | AE44: Included | AF44: Included | AG44: Not stated | AH44: Included | AI44: Not stated
A45: 44 | B45: Laura Lopez | C45: Word doc: Villa Study Scratch List (Updated Oct 2023) | D45: Oct 2023 (doc); received by email Sept 2026 | E45: Jennings at Notre Dame Village | F45: Jennings/Sisters of Notre Dame | G45: Chardon, OH | H45: CCRC | I45: 40 villas (2100 sq ft) | J45: Below-listed rates are “effective July 1, 2022” . | $2950 | K45: 2950 | L45: 2950 | M45: CCRC (entry fee not stated) | O45: Campus amenities (therapy/rehab; fitness studio; etc.) | R45: (via campus amenities) Campus amenities (therapy/rehab; fitness studio; etc.) | U45: Water and sewer | W45: Attached 2 ½ car garage; In-unit washer/drier in laundry room; Private porch | Y45: Cleveland – Shaker Heights | AA45: Not stated | AB45: Included | AC45: Not stated | AD45: Not stated | AE45: Included | AF45: Not stated | AG45: Not stated | AH45: Included | AI45: Not stated
A46: 45 | B46: Laura Lopez | C46: Word doc: Villa Study Scratch List (Updated Oct 2023) | D46: Oct 2023 (doc); received by email Sept 2026 | E46: Vitalia at Stow | F46: Arrow Senior Living | G46: Stow, OH | H46: rental-only continuum | I46: 6 villas | M46: Not stated | O46: Campus amenities (wellness center; library; demonstration kitchen; indoor pool; bistro; movie theater; billiards) | R46: (via campus amenities) Campus amenities (wellness center; library; demonstration kitchen; indoor pool; bistro; movie theater; billiards) | W46: Attached garage; 2-3 Bed/ 2 Bath | Y46: Hudson/SE Cleveland – Fall 2021 | Z46: 2019 | AA46: Not stated | AB46: Included | AC46: Not stated | AD46: Not stated | AE46: Included | AF46: Not stated | AG46: Not stated | AH46: Not stated | AI46: Not stated
A47: 46 | B47: Laura Lopez | C47: Word doc: Villa Study Scratch List (Updated Oct 2023) | D47: Oct 2023 (doc); received by email Sept 2026 | E47: Vitalia at Montrose | F47: Arrow Senior Living | G47: Copley, OH | H47: rental-only continuum | I47: 19 villas | M47: Not stated | O47: Campus amenities (wellness center; library; demonstration kitchen; indoor pool; bistro; movie theater; billiards) | R47: (via campus amenities) Campus amenities (wellness center; library; demonstration kitchen; indoor pool; bistro; movie theater; billiards) | W47: Attached garage; 2-3 Bed/ 2 Bath | Y47: Echelon of Medina, OH (SE Cleveland) | Z47: Opened 2020 | AA47: Not stated | AB47: Included | AC47: Not stated | AD47: Not stated | AE47: Included | AF47: Not stated | AG47: Not stated | AH47: Not stated | AI47: Not stated
A48: 47 | B48: Laura Lopez | C48: Word doc: Villa Study Scratch List (Updated Oct 2023) | D48: Oct 2023 (doc); received by email Sept 2026 | E48: Kirkland Crossings | F48: Presbyterian Homes & Services | G48: Pewaukee, WI | H48: rental-only continuum | I48: 22 villas (1-57 – 1667 sq ft) | M48: Not stated | N48: Transportation | U48: Cable; Telephone service; Property tax and building insurance | W48: Attached garage; In-unit washer/dryer | Y48: Milwaukee 2022 Market Shops (Pewaukee) | Z48: Opened 2001 | AA48: Included | AB48: Not stated | AC48: Not stated | AD48: Not stated | AE48: Not stated | AF48: Not stated | AG48: Not stated | AH48: Included | AI48: Not stated
A49: 48 | B49: Laura Lopez | C49: Word doc: Villa Study Scratch List (Updated Oct 2023) | D49: Oct 2023 (doc); received by email Sept 2026 | E49: The Waters of Pewaukee | F49: The Waters Senior Living Management, LLC | G49: Waukesha, WI | H49: rental-only continuum | I49: 30 villas | M49: Not stated | W49: Attached garage; In-unit washer/dryer | Y49: Milwaukee 2022 Market Shops (Pewaukee) | Z49: 2023? | AA49: Not stated | AB49: Not stated | AC49: Not stated | AD49: Not stated | AE49: Not stated | AF49: Not stated | AG49: Not stated | AH49: Not stated | AI49: Not stated
A50: 49 | B50: Laura Lopez | C50: Word doc: Villa Study Scratch List (Updated Oct 2023) | D50: Oct 2023 (doc); received by email Sept 2026 | E50: Three Pillars Senior Living | F50: Three Pillars Senior Living Communities | G50: Dousman, WI | H50: CCRC | I50: 61 villas (1058 – 1375 sq ft) | J50: Entry Fee: $284,000 - $695,000 | M50: Yes | N50: Transportation | T50: Interior/exterior maintenance/groundskeeping | U50: Property taxes, water, and sewer | W50: Private porch/patio; Washer/dryer w/ laundry room | Y50: Milwaukee 2022 Market Shops (Delafield) | Z50: Opened 1991 | AA50: Included | AB50: Not stated | AC50: Not stated | AD50: Not stated | AE50: Not stated | AF50: Not stated | AG50: Included | AH50: Included | AI50: Not stated
A51: 50 | B51: Laura Lopez | C51: Word doc: Villa Study Scratch List (Updated Oct 2023) | D51: Oct 2023 (doc); received by email Sept 2026 | E51: Traditions at North Willow | F51: Traditions | G51: Indianapolis, IN | H51: rental-only continuum | I51: 50 villas (850 – 1300 sq ft) | M51: Not stated | O51: Clubhouse with fitness center; Enclosed dog park | R51: (via campus amenities) Clubhouse with fitness center | S51: Gated security; Emergency call system | T51: Interior/exterior maintenance/groundskeeping | U51: All utilities | W51: Attached single-car garage; In-unit washer/dryer | Y51: Indianapolis – Anthology Meridian Hills Acquisition | Z51: 2018 | AA51: Not stated | AB51: Included | AC51: Not stated | AD51: Not stated | AE51: Included | AF51: Included | AG51: Included | AH51: Included | AI51: Not stated
A52: 51 | B52: Laura Lopez | C52: Word doc: Villa Study Scratch List (Updated Oct 2023) | D52: Oct 2023 (doc); received by email Sept 2026 | E52: Traditions at Solana | F52: Traditions | G52: Indianapolis, IN | H52: rental-only continuum | I52: 24 villas (1134 – 1818 sq ft) | M52: Not stated | P52: 30 meals/month | Q52: Interior/exterior maintenance/housekeeping | S52: Emergency call system | T52: Interior/exterior maintenance/housekeeping | W52: Attached one-car garage; In-unit washer/dryer | Y52: Indianapolis – Anthology Meridian Hills Acquisition | Z52: 2016 | AA52: Not stated | AB52: Not stated | AC52: Included | AD52: Included | AE52: Not stated | AF52: Included | AG52: Included | AH52: Not stated | AI52: Not stated
A53: 52 | B53: Laura Lopez | C53: Word doc: Villa Study Scratch List (Updated Oct 2023) | D53: Oct 2023 (doc); received by email Sept 2026 | E53: Marquette | F53: Life Care Services LLC | G53: Indianapolis, IN | H53: Entry Fee CCRC | I53: 36 villas | M53: Yes | S53: Emergency call system | T53: “Maintenance-free living” | U53: Internet and all utilities | W53: Attached one- or two-car garage; In-unit washer/dryer | Y53: Indianapolis – Anthology Meridian Acquisition | Z53: 1981 | AA53: Not stated | AB53: Not stated | AC53: Not stated | AD53: Not stated | AE53: Not stated | AF53: Included | AG53: Included | AH53: Included | AI53: Not stated
A54: 53 | B54: Laura Lopez | C54: Word doc: Villa Study Scratch List (Updated Oct 2023) | D54: Oct 2023 (doc); received by email Sept 2026 | E54: Five Star Residences of Clearwater | F54: Five Star Senior Living | G54: Indianapolis, IN | H54: Villa & AL | I54: 11 villas | M54: Not stated | P54: Three daily meals | Q54: Weekly housekeeping and flat linen service; Interior/exterior maintenance/housekeeping | T54: Interior/exterior maintenance/housekeeping | V54: 24/7 concierge service | W54: Attached garage | Y54: Indianapolis Anthology Meridian Acquisition | Z54: Opened 1995 | AA54: Not stated | AB54: Not stated | AC54: Included | AD54: Included | AE54: Not stated | AF54: Not stated | AG54: Included | AH54: Not stated | AI54: Included
A55: 54 | B55: Laura Lopez | C55: Word doc: Villa Study Scratch List (Updated Oct 2023) | D55: Oct 2023 (doc); received by email Sept 2026 | E55: The Stratford | F55: Weller Life Communities | G55: Carmel, IN | H55: CCRC | I55: 40 villas (1132 – 2346 sq ft) | J55: Cottage Homes start at $3690 | K55: 3690 | L55: 3690 | M55: CCRC (entry fee not stated) | N55: Transportation | P55: “Daily dining” ($600 monthly towards onsite dining menus) | Q55: Weekly and annual spring cleaning | T55: “Maintenance-Free Living” and landscaping | U55: Utilities, property taxes/insurance, and cable | W55: Attached garage; In-unit washer/dryer | Y55: North Indianapolis, IN (Carmel, IN) | Z55: 2008 | AA55: Included | AB55: Not stated | AC55: Included | AD55: Included | AE55: Not stated | AF55: Not stated | AG55: Included | AH55: Included | AI55: Not stated
A56: 55 | B56: Laura Lopez | C56: Word doc: Villa Study Scratch List (Updated Oct 2023) | D56: Oct 2023 (doc); received by email Sept 2026 | E56: Hoosier Village | F56: BHI Senior Living | G56: Indianapolis, IN | H56: Entry Fee CCRC | I56: 212 villas | M56: Yes | Q56: Interior/exterior maintenance/housekeeping | S56: Emergency call system | T56: Interior/exterior maintenance/housekeeping | U56: Utilities (except electric and phone) | W56: Attached two-car garage; Full-sized washer/dryer | Y56: North Indianapolis, IN (Carmel, IN) | Z56: 1952 | AA56: Not stated | AB56: Not stated | AC56: Not stated | AD56: Included | AE56: Not stated | AF56: Included | AG56: Included | AH56: Included | AI56: Not stated
A57: 56 | B57: Laura Lopez | C57: Word doc: Villa Study Scratch List (Updated Oct 2023) | D57: Oct 2023 (doc); received by email Sept 2026 | E57: Five Star Senior Residences of Noblesville | F57: Five Star Senior Living | G57: Noblesville, IN | H57: rental-only continuum | I57: 54 villas | J57: Starting at $2050 | K57: 2050 | L57: 2050 | M57: Not stated | Q57: Interior/exterior maintenance/housekeeping; Weekly housekeeping and flat linen service | T57: Interior/exterior maintenance/housekeeping | V57: 24/7 concierge service | W57: Patio/porch; In-unit washer/dryer | Y57: North Indianapolis, IN (Carmel, IN) | Z57: 2004 | AA57: Not stated | AB57: Not stated | AC57: Not stated | AD57: Included | AE57: Not stated | AF57: Not stated | AG57: Included | AH57: Not stated | AI57: Included
A58: 57 | B58: Laura Lopez | C58: Word doc: Villa Study Scratch List (Updated Oct 2023) | D58: Oct 2023 (doc); received by email Sept 2026 | E58: Zionsville Meadows | F58: American Senior Communities | G58: Zionsville, IN | H58: rental-only continuum | I58: 60 villas | J58: Garden Homes start at $1727.25 | K58: 1727.25 | L58: 1727.25 | M58: Not stated | N58: Transportation | Q58: Interior/exterior maintenance/housekeeping | S58: 24 hour emergency response system | T58: Interior/exterior maintenance/housekeeping | U58: All utilities except telephone and cable | W58: In-unit washer/dryer; Detached garages available | Y58: North Indianapolis, IN (Carmel, IN) | Z58: 1975 | AA58: Included | AB58: Not stated | AC58: Not stated | AD58: Included | AE58: Not stated | AF58: Included | AG58: Included | AH58: Included | AI58: Not stated
A59: 58 | B59: Laura Lopez | C59: Word doc: Villa Study Scratch List (Updated Oct 2023) | D59: Oct 2023 (doc); received by email Sept 2026 | E59: Hamilton Trace | F59: CarDon and Associates Inc. | G59: Fishers, IN | H59: rental-only continuum | I59: 42 villas | M59: Not stated | N59: Transportation | Q59: Interior/exterior maintenance/housekeeping; Bi-weekly housekeeping | S59: Emergency response system | T59: Interior/exterior maintenance/housekeeping | U59: Water and sewer | W59: Attached garage; Washer/dryer hookups | Y59: North Indianapolis, IN (Carmel, IN) | Z59: 2011 (main campus); villas opened 2015 | AA59: Included | AB59: Not stated | AC59: Not stated | AD59: Included | AE59: Not stated | AF59: Included | AG59: Included | AH59: Included | AI59: Not stated
A60: 59 | B60: Laura Lopez | C60: Word doc: Villa Study Scratch List (Updated Oct 2023) | D60: Oct 2023 (doc); received by email Sept 2026 | E60: Traditions at Brookside | F60: Traditions Management | G60: McCordsville, IN | H60: rental-only continuum | I60: 42 villas | M60: Not stated | N60: Transportation | S60: Emergency response system | W60: Attached one-car garage; In-unit washer/dryer | Y60: North Indianapolis, IN (Carmel, IN) | Z60: 2017 (main campus); villas opened 2019 | AA60: Included | AB60: Not stated | AC60: Not stated | AD60: Not stated | AE60: Not stated | AF60: Included | AG60: Not stated | AH60: Not stated | AI60: Not stated
A61: 60 | B61: Laura Lopez | C61: Word doc: Villa Study Scratch List (Updated Oct 2023) | D61: Oct 2023 (doc); received by email Sept 2026 | E61: Avon Health and Rehabilitation | F61: TLC Management | G61: Avon, IN | H61: rental-only continuum | I61: 8 villas | M61: Not stated | N61: Transportation | P61: Meals | Q61: Weekly Housekeeping and linen services | U61: Paid utilities | W61: Attached garage | Y61: Capital Properties Acquisition Project (Prestwick/West Indiana) | Z61: 2007 | AA61: Included | AB61: Not stated | AC61: Included | AD61: Included | AE61: Not stated | AF61: Not stated | AG61: Not stated | AH61: Included | AI61: Not stated
A62: 61 | B62: Laura Lopez | C62: Word doc: Villa Study Scratch List (Updated Oct 2023) | D62: Oct 2023 (doc); received by email Sept 2026 | E62: Brownsburg Meadows | F62: American Senior Communities | G62: Brownsburg, IN | H62: rental-only continuum | I62: 23 villas | J62: Garden Homes start at $2065 | K62: 2065 | L62: 2065 | M62: Not stated | N62: Transportation | U62: All utilities except telephone and cable | W62: Some w/ attached garages | Y62: Capital Properties Acquisition Project (Prestwick/West Indiana) | Z62: 2006 | AA62: Included | AB62: Not stated | AC62: Not stated | AD62: Not stated | AE62: Not stated | AF62: Not stated | AG62: Not stated | AH62: Included | AI62: Not stated
A63: 62 | B63: Laura Lopez | C63: Word doc: Villa Study Scratch List (Updated Oct 2023) | D63: Oct 2023 (doc); received by email Sept 2026 | E63: Sugar Grove Senior Living | F63: Tutera Senior Living & Health Care | G63: Plainfield, IN | H63: rental-only continuum | I63: 48 villas (832 – 1363 sq ft) | M63: Not stated | S63: Emergency response system | U63: All utilities, including basic cable, telephone, and Wi-Fi | W63: Washer/dryer hookups; Some include attached garage | Y63: Capital Properties Acquisition Project (Prestwick/West Indiana) | Z63: 2010 | AA63: Not stated | AB63: Not stated | AC63: Not stated | AD63: Not stated | AE63: Not stated | AF63: Included | AG63: Not stated | AH63: Included | AI63: Not stated
A64: 63 | B64: Laura Lopez | C64: Word doc: Villa Study Scratch List (Updated Oct 2023) | D64: Oct 2023 (doc); received by email Sept 2026 | E64: Summit Place West | F64: Magnolia Management Inc | G64: Indianapolis, IN | H64: rental-only continuum | I64: 35 villas | M64: Not stated | X64: None confirmed on website – call for more info | Y64: Capital Properties Acquisition Project (Prestwick/West Indiana) | Z64: 1998 | AA64: Not stated | AB64: Not stated | AC64: Not stated | AD64: Not stated | AE64: Not stated | AF64: Not stated | AG64: Not stated | AH64: Not stated | AI64: Not stated
A65: 64 | B65: Laura Lopez | C65: Word doc: Villa Study Scratch List (Updated Oct 2023) | D65: Oct 2023 (doc); received by email Sept 2026 | E65: Traditions at Reagan Park | F65: Traditions Management | G65: Avon, IN | H65: rental-only continuum | I65: 44 villas (927 – 1615 sq ft) | M65: Not stated | N65: Transportation | P65: 30 meals/month | Q65: Interior/exterior maintenance/housekeeping | S65: Emergency Pendant | T65: Interior/exterior maintenance/housekeeping | U65: All utilities | W65: In-unit washer/dryer; Some w/ attached garages | Y65: Capital Properties Acquisition Project (Prestwick/West Indiana) | Z65: 2014 | AA65: Included | AB65: Not stated | AC65: Included | AD65: Included | AE65: Not stated | AF65: Included | AG65: Included | AH65: Included | AI65: Not stated
A66: 65 | B66: Laura Lopez | C66: Word doc: Villa Study Scratch List (Updated Oct 2023) | D66: Oct 2023 (doc); received by email Sept 2026 | E66: Woodland Terrace of Danville | F66: New Perspective Senior Living | G66: Danville, IN | H66: rental-only continuum | I66: 16 villas (1225 – 1663 sq ft); 14 two-bedroom units, 2 three-bedroom units | J66: Rent starting at $2730 | K66: 2730 | L66: 2730 | M66: Not stated | N66: Transportation | Q66: Bi-Weekly housekeeping; Interior/exterior maintenance/housekeeping | T66: Interior/exterior maintenance/housekeeping | U66: Utilities paid; Wi-Fi | W66: Attached two-car garage; In-unit washer/dryer | Y66: Capital Properties Acquisition Project (Prestwick/West Indiana) | Z66: 2020 (main building opened 2022) | AA66: Included | AB66: Not stated | AC66: Not stated | AD66: Included | AE66: Not stated | AF66: Not stated | AG66: Included | AH66: Included | AI66: Not stated
A67: 66 | B67: Laura Lopez | C67: Word doc: Villa Study Scratch List (Updated Oct 2023) | D67: Oct 2023 (doc); received by email Sept 2026 | E67: Westminster Village North | F67: Westminster Village North Board of Directors | G67: Indianapolis, IN | H67: Entry Fee CCRC | I67: 41 villas ( 1333 – 1700 sq ft) | J67: Entry Fees: $165,000 - $200,000+ | M67: Yes | W67: Attached garage | Y67: Capital Properties Acquisition Project (Windermere/Fishers) | Z67: 1972 | AA67: Not stated | AB67: Not stated | AC67: Not stated | AD67: Not stated | AE67: Not stated | AF67: Not stated | AG67: Not stated | AH67: Not stated | AI67: Not stated
A68: 67 | B68: Laura Lopez | C68: Word doc: Villa Study Scratch List (Updated Oct 2023) | D68: Oct 2023 (doc); received by email Sept 2026 | E68: Green Oaks Senior Living | F68: Spectrum | G68: Libertyville, IL | H68: rental-only continuum | I68: 12 villas | M68: Not stated | X68: None confirmed | Y68: Capital Properties Acquisition Project (Libertyville) | Z68: 2017 | AA68: Not stated | AB68: Not stated | AC68: Not stated | AD68: Not stated | AE68: Not stated | AF68: Not stated | AG68: Not stated | AH68: Not stated | AI68: Not stated
A69: 68 | B69: Laura Lopez | C69: Word doc: Villa Study Scratch List (Updated Oct 2023) | D69: Oct 2023 (doc); received by email Sept 2026 | E69: Lake Forest Place | F69: Presbyterian Homes | G69: Lake Forest, IL | H69: Entry Fee CCRC | I69: 114 villas (1722 – 2392 sq ft) | J69: Monthly fee starting at $6860; Entrance Fees starting at $545,800 | K69: 6860 | L69: 6860 | M69: Yes | P69: $490 in meals | Q69: Weekly Housekeeping services | S69: Emergency Call System | T69: Interior/exterior maintenance | U69: Utilities included | W69: Attached two-car garage; In-unit washer/dryer w/ laundry room; Private patio | Y69: Capital Properties Acquisition Project (Libertyville) | Z69: 1998 | AA69: Not stated | AB69: Not stated | AC69: Included | AD69: Included | AE69: Not stated | AF69: Included | AG69: Included | AH69: Included | AI69: Not stated
A70: 69 | B70: Laura Lopez | C70: Word doc: Villa Study Scratch List (Updated Oct 2023) | D70: Oct 2023 (doc); received by email Sept 2026 | E70: Villa St. Benedict | F70: Benedictine Health Systems & Benedictine Sisters of Saint Scholastica | G70: Lisle, IL | H70: Entry Fee CCRC | I70: 56 villas (1200 – 1360 sq ft) | M70: Yes | N70: Transportation | P70: Continental breakfast | Q70: Weekly housekeeping and linen service | S70: Emergency response system, including cable, internet, and phone | T70: Interior/exterior maintenance | U70: Emergency response system, including cable, internet, and phone; All utilities | W70: Attached garage; In-unit washer/dryer | Y70: Capital Properties Acquisition Project (Naperville) | Z70: 2005 | AA70: Included | AB70: Not stated | AC70: Included | AD70: Included | AE70: Not stated | AF70: Included | AG70: Included | AH70: Included | AI70: Not stated
A71: 70 | B71: Laura Lopez | C71: Word doc: Villa Study Scratch List (Updated Oct 2023) | D71: Oct 2023 (doc); received by email Sept 2026 | E71: Wyndemere | F71: Life Care Services LLC | G71: Wheaton, IL | H71: Entry Fee CCRC | I71: 26 villas | M71: Yes | N71: Transportation | T71: Interior/exterior maintenance | W71: Attached two-car garage; In-unit washer/dryer w/ laundry room | Y71: Capital Properties Acquisition Project (Naperville) | Z71: 1968 | AA71: Included | AB71: Not stated | AC71: Not stated | AD71: Not stated | AE71: Not stated | AF71: Not stated | AG71: Included | AH71: Not stated | AI71: Not stated
A72: 71 | B72: Laura Lopez | C72: Word doc: Villa Study Scratch List (Updated Oct 2023) | D72: Oct 2023 (doc); received by email Sept 2026 | E72: Alden of Waterford | F72: Alden Management Services Inc. | G72: Aurora, IL | H72: Entry Fee CCRC | I72: 67 villas | M72: Yes | X72: Amenities not confirmed online | Y72: Capital Properties Acquisition Project (Naperville) | Z72: 2002 | AA72: Not stated | AB72: Not stated | AC72: Not stated | AD72: Not stated | AE72: Not stated | AF72: Not stated | AG72: Not stated | AH72: Not stated | AI72: Not stated
A73: 72 | B73: Laura Lopez | C73: Word doc: Villa Study Scratch List (Updated Oct 2023) | D73: Oct 2023 (doc); received by email Sept 2026 | E73: Tabor Hills | F73: Tabor Hills Corporate | G73: Naperville, IL | H73: CCRC | I73: 104 villas | M73: CCRC (entry fee not stated) | S73: Emergency response system | T73: Landscaping and grounds maintenance | U73: In-unit washer/dryer w/ utility room; Water, sewer, and trash service | W73: Attached, “extra-deep” garage; In-unit washer/dryer w/ utility room | Y73: Capital Properties Acquisition Project (Naperville) | Z73: 1994 | AA73: Not stated | AB73: Not stated | AC73: Not stated | AD73: Not stated | AE73: Not stated | AF73: Included | AG73: Included | AH73: Included | AI73: Not stated
A74: 73 | B74: Laura Lopez | C74: Word doc: Villa Study Scratch List (Updated Oct 2023) | D74: Oct 2023 (doc); received by email Sept 2026 | E74: Green Hills Community | F74: Life Care Services | G74: Ames, IA | H74: Entry Fee CCRC | I74: 82 villas (1306 – 2986 sq ft) | M74: Yes | T74: Interior/exterior maintenance | U74: Property taxes | W74: Attached garage; In-unit washer/dryer; Many w/ basements | Y74: Capital Properties Acquisition Project (Ames) | Z74: 1986 | AA74: Not stated | AB74: Not stated | AC74: Not stated | AD74: Not stated | AE74: Not stated | AF74: Not stated | AG74: Included | AH74: Included | AI74: Not stated
A75: 74 | B75: Laura Lopez | C75: Word doc: Villa Study Scratch List (Updated Oct 2023) | D75: Oct 2023 (doc); received by email Sept 2026 | E75: Northcrest Community | F75: Northcrest Foundation | G75: Ames, IA | H75: Entry Fee CCRC | I75: 42 villas (1100 – 1850 sq ft) | M75: Yes | W75: Attached one- and two-car garages; Many w/ two levels; In-unit washer/dryer; Private patio | Y75: Capital Properties Acquisition Project (Ames) | Z75: 1965 | AA75: Not stated | AB75: Not stated | AC75: Not stated | AD75: Not stated | AE75: Not stated | AF75: Not stated | AG75: Not stated | AH75: Not stated | AI75: Not stated
A76: 75 | B76: Laura Lopez | C76: Word doc: Villa Study Scratch List (Updated Oct 2023) | D76: Oct 2023 (doc); received by email Sept 2026 | E76: Pacific Springs Village | F76: Immanuel Communities | G76: Omaha, NE | H76: Rental-only continuum | I76: 52 villas (920 – 2323 sq ft) | M76: Not stated | N76: Transportation | Q76: “Home maintenance, including grounds, housekeeping and repairs” | S76: Emergency alert system; 24 hour security | T76: “Home maintenance, including grounds, housekeeping and repairs” | U76: Utilities, including cable | W76: Some w/ two levels; Attached garages | Y76: Capital Properties Acquisition Project (Omaha) | Z76: 2013 (patio homes); community opened 2002 | AA76: Included | AB76: Not stated | AC76: Not stated | AD76: Included | AE76: Not stated | AF76: Included | AG76: Included | AH76: Included | AI76: Not stated
A77: 76 | B77: Laura Lopez | C77: Word doc: Villa Study Scratch List (Updated Oct 2023) | D77: Oct 2023 (doc); received by email Sept 2026 | E77: Hillcrest Country Village | F77: Hillcrest Health Services | G77: Papillion, NE | H77: CCRC | I77: 42 villas | M77: CCRC (entry fee not stated) | T77: Interior/exterior upkeep | U77: Trash service; Taxes/insurance included | W77: Finished basements available; Attached two-car garage | Y77: Capital Properties Acquisition Project (Omaha) | Z77: Opened 2008 | AA77: Not stated | AB77: Not stated | AC77: Not stated | AD77: Not stated | AE77: Not stated | AF77: Not stated | AG77: Included | AH77: Included | AI77: Not stated
A78: 77 | B78: Laura Lopez | C78: Word doc: Villa Study Scratch List (Updated Oct 2023) | D78: Oct 2023 (doc); received by email Sept 2026 | E78: Richmont Village | F78: MJ Senior Housing | G78: Bellevue, NE | H78: rental-only continuum | I78: 10 villas | M78: Not stated | W78: Attached two-car garage | Y78: Capital Properties Acquisition Project (Omaha) | Z78: 2002 | AA78: Not stated | AB78: Not stated | AC78: Not stated | AD78: Not stated | AE78: Not stated | AF78: Not stated | AG78: Not stated | AH78: Not stated | AI78: Not stated
A79: 78 | B79: Laura Lopez | C79: Word doc: Villa Study Scratch List (Updated Oct 2023) | D79: Oct 2023 (doc); received by email Sept 2026 | E79: Georgetown Place | F79: Sonida Senior Living | G79: Fort Wayne, IN | H79: rental-only continuum | I79: 13 villas (1286 sq ft) | M79: Not stated | W79: Attached garage; Patio; In-unit washer/dryer | Y79: Capital Properties Acquisition Project (Fort Wayne) | Z79: 1986 | AA79: Not stated | AB79: Not stated | AC79: Not stated | AD79: Not stated | AE79: Not stated | AF79: Not stated | AG79: Not stated | AH79: Not stated | AI79: Not stated
A80: 79 | B80: Laura Lopez | C80: Word doc: Villa Study Scratch List (Updated Oct 2023) | D80: Oct 2023 (doc); received by email Sept 2026 | E80: Five Star Residences of Fort Wayne | F80: Five Star Senior Living | G80: Fort Wayne, IN | H80: rental-only continuum | I80: 24 villas (1200 – 1355 sq ft) | J80: Starting at $2180 | K80: 2180 | L80: 2180 | M80: Not stated | Q80: Weekly housekeeping and linen services | T80: “Maintenance of home, building and grounds” | V80: 24/7 concierge service | W80: Attached garage; In-unit washer/dryer | Y80: Capital Properties Acquisition Project (Fort Wayne) | Z80: 1997 | AA80: Not stated | AB80: Not stated | AC80: Not stated | AD80: Included | AE80: Not stated | AF80: Not stated | AG80: Included | AH80: Not stated | AI80: Included
A81: 80 | B81: Laura Lopez | C81: Word doc: Villa Study Scratch List (Updated Oct 2023) | D81: Oct 2023 (doc); received by email Sept 2026 | E81: Towne House Retirement Center | F81: BHI Senior Living | G81: Fort Wayne, IN | H81: Entry Fee CCRC | I81: 92 villas (1850 – 2558 sq ft) 12 onsite (Chapmans Crossing); 80 at Prairie Landing (1335 Prairie Landing Parkway, Fort Wayne, IN 46804) | M81: Yes | U81: Utilities (some include basic cable and local phone service) | W81: Attached two-car garage; In-unit washer/dryer; Patio; Some w/ extra level above garage | Y81: Capital Properties Acquisition Project (Fort Wayne) | Z81: 2006 | AA81: Not stated | AB81: Not stated | AC81: Not stated | AD81: Not stated | AE81: Not stated | AF81: Not stated | AG81: Not stated | AH81: Included | AI81: Not stated
A82: 81 | B82: Laura Lopez | C82: Word doc: Villa Study Scratch List (Updated Oct 2023) | D82: Oct 2023 (doc); received by email Sept 2026 | E82: Coventry Meadows | F82: American Senior Communities | G82: Fort Wayne, IN | H82: rental-only continuum | I82: 36 villas (650 – 2970 sq ft) | M82: Not stated | N82: Transportation | T82: Interior/exterior maintenance | U82: All utilities included except cable, phone, and Wi-Fi | W82: Some w/ two levels; Most w/ attached garages | Y82: Capital Properties Acquisition Project (Fort Wayne) | Z82: 2007 | AA82: Included | AB82: Not stated | AC82: Not stated | AD82: Not stated | AE82: Not stated | AF82: Not stated | AG82: Included | AH82: Included | AI82: Not stated
A83: 82 | B83: Laura Lopez | C83: Word doc: Villa Study Scratch List (Updated Oct 2023) | D83: Oct 2023 (doc); received by email Sept 2026 | E83: Piper Trail | F83: Lutheran Life Villages | G83: Fort Wayne, IN | H83: Entry Fee CCRC | I83: 48 villas (1140 – 1676 sq ft) | J83: $1575 per month, based on an 80% refundable entrance fee | K83: 1575 | L83: 1575 | M83: Yes | T83: Interior/exterior maintenance | U83: All utilities | W83: In-unit washer/dryer; Rear-attached two-car garage | X83: Part of a larger CCRC campus w/ Lutheran Life Villages – The Village at Inverness | Y83: Capital Properties Acquisition Project (Fort Wayne) | Z83: 2018 (villas); larger campus opened 2014 | AA83: Not stated | AB83: Not stated | AC83: Not stated | AD83: Not stated | AE83: Not stated | AF83: Not stated | AG83: Included | AH83: Included | AI83: Not stated
A84: 83 | B84: Laura Lopez | C84: Word doc: Villa Study Scratch List (Updated Oct 2023) | D84: Oct 2023 (doc); received by email Sept 2026 | E84: Holy Cross Village – Notre Dame | F84: Brothers of the Holy Cross | G84: Notre Dame, IN | H84: Entry Fee CCRC | I84: 38 villas (22 freestanding, 12 duplexes, one Quad 4-unit building) | M84: Yes | S84: 24/7 security; Emergency response system | U84: All utilities, including cable (excluding telephone and internet) | W84: Attached garage | Z84: 1997 | AA84: Not stated | AB84: Not stated | AC84: Not stated | AD84: Not stated | AE84: Not stated | AF84: Included | AG84: Not stated | AH84: Included | AI84: Not stated
A85: 84 | B85: Laura Lopez | C85: Word doc: Villa Study Scratch List (Updated Oct 2023) | D85: Oct 2023 (doc); received by email Sept 2026 | E85: Primrose Retirement Community of Mishawaka | F85: Primrose Retirement Communities | G85: Mishawaka, IN | H85: rental-only continuum | I85: 8 villas (all 2 Bed/ 2 Bath, 1594 sq ft) | M85: Not stated | N85: Transportation | S85: Emergency response system | T85: Lawn care | U85: Utilities, including cable (excluding telephone and internet) | W85: Attached garage; In-unit washer/dryer; Front porch; Four season room; Gas fireplace | Z85: 2015 | AA85: Included | AB85: Not stated | AC85: Not stated | AD85: Not stated | AE85: Not stated | AF85: Included | AG85: Included | AH85: Included | AI85: Not stated
A86: 85 | B86: Laura Lopez | C86: Word doc: Villa Study Scratch List (Updated Oct 2023) | D86: Oct 2023 (doc); received by email Sept 2026 | E86: Southfield Village | F86: Greencroft Communities | G86: South Bend, IN | H86: rental-only continuum | I86: 14 villas | M86: Not stated | U86: All utilities included | W86: Full basement; Patio or porch; Attached one- and two-car garages | Z86: 2009 (villas); main campus opened 2000 | AA86: Not stated | AB86: Not stated | AC86: Not stated | AD86: Not stated | AE86: Not stated | AF86: Not stated | AG86: Not stated | AH86: Included | AI86: Not stated
A87: 86 | B87: Laura Lopez | C87: Word doc: Villa Study Scratch List (Updated Oct 2023) | D87: Oct 2023 (doc); received by email Sept 2026 | E87: Hubbard Hill | F87: Hubbard Hill | G87: Elkhart, IN | H87: Entry Fee CCRC | I87: 84 villas (42 duplexes); 1380 sq ft | M87: Yes | T87: Exterior maintenance | U87: City water & sewer; insurance | W87: Some units include basements; Attached one-car garage (416 sq ft) | Y87: Harmony at Elkhart IN | Z87: Opened 1977 | AA87: Not stated | AB87: Not stated | AC87: Not stated | AD87: Not stated | AE87: Not stated | AF87: Not stated | AG87: Included | AH87: Included | AI87: Not stated
A88: 87 | B88: Laura Lopez | C88: Word doc: Villa Study Scratch List (Updated Oct 2023) | D88: Oct 2023 (doc); received by email Sept 2026 | E88: Five Star Residences of Banta Pointe | F88: Five Star Senior Living | G88: Indianapolis, IN | H88: rental-only continuum | I88: 22 villas (922 – 1106 sq ft) | J88: Monthly rates starting at $2315 | K88: 2315 | L88: 2315 | M88: Not stated | P88: One daily meal | Q88: Weekly housekeeping and flat linen service | T88: “Maintenance of home, building and grounds | V88: 24/7 concierge service | W88: Attached garages; In-unit washer/dryer; Sunroom | Y88: Capital Properties Acquisition Project (Greenwood/Zionsville IN) | Z88: 1995 | AA88: Not stated | AB88: Not stated | AC88: Included | AD88: Included | AE88: Not stated | AF88: Not stated | AG88: Included | AH88: Not stated | AI88: Included
A89: 88 | B89: Laura Lopez | C89: Word doc: Villa Study Scratch List (Updated Oct 2023) | D89: Oct 2023 (doc); received by email Sept 2026 | E89: Otterbein Franklin | F89: Otterbein SeniorLife | G89: Franklin, IN | H89: Entry Fee CCRC | I89: 158 villas (1304 – 1976 sq ft) | M89: Yes | T89: Interior/exterior maintenance | U89: “Some utilities covered” | W89: Attached garage; Washer/dryer hookups | Y89: Capital Properties Acquisition Project (Greenwood/Zionsville IN) | Z89: 1956 | AA89: Not stated | AB89: Not stated | AC89: Not stated | AD89: Not stated | AE89: Not stated | AF89: Not stated | AG89: Included | AH89: Included | AI89: Not stated
A90: 89 | B90: Laura Lopez | C90: Word doc: Villa Study Scratch List (Updated Oct 2023) | D90: Oct 2023 (doc); received by email Sept 2026 | E90: Greenwood Village South | F90: Life Care Services | G90: Greenwood, IN | H90: Entry Fee CCRC | I90: 78 villas | M90: Yes | S90: Emergency call system | T90: Exterior/interior maintenance | U90: Basic cable, water, and electric | W90: In-unit washer/dryer; Attached two-car garage | Y90: Capital Properties Acquisition Project (Greenwood/Zionsville IN) | Z90: 1996 | AA90: Not stated | AB90: Not stated | AC90: Not stated | AD90: Not stated | AE90: Not stated | AF90: Included | AG90: Included | AH90: Included | AI90: Not stated
A91: 90 | B91: Laura Lopez | C91: Word doc: Villa Study Scratch List (Updated Oct 2023) | D91: Oct 2023 (doc); received by email Sept 2026 | E91: Compass Park | F91: Indiana Free Masons | G91: Franklin, IN | H91: CCRC | I91: 98 villas (900 – 1800 sq ft) | M91: CCRC (entry fee not stated) | S91: Emergency Call Service; 24/7 security | T91: Interior/exterior maintenance | U91: Water & sewer; Trash pickup | W91: Covered parking, most w/ attached garages | Z91: Opened 1916 | AA91: Not stated | AB91: Not stated | AC91: Not stated | AD91: Not stated | AE91: Not stated | AF91: Included | AG91: Included | AH91: Included | AI91: Not stated
A92: 91 | B92: Laura Lopez | C92: Word doc: Villa Study Scratch List (Updated Oct 2023) | D92: Oct 2023 (doc); received by email Sept 2026 | E92: Rosegate Assisted Living | F92: American Senior Communities | G92: Indianapolis, IN | H92: ALF/SNF w/ villa | I92: 79 villas (12 one-bedroom and 67 two-bedroom) | J92: Garden homes starting at $1865 | K92: 1865 | L92: 1865 | M92: Not stated | N92: Transportation | T92: Interior/exterior maintenance | U92: “All utilities included except telephone” | Z92: 1999 | AA92: Included | AB92: Not stated | AC92: Not stated | AD92: Not stated | AE92: Not stated | AF92: Not stated | AG92: Included | AH92: Included | AI92: Not stated
A93: 92 | B93: Laura Lopez | C93: Word doc: Villa Study Scratch List (Updated Oct 2023) | D93: Oct 2023 (doc); received by email Sept 2026 | E93: Altenheim Community | F93: CarDon and Associates Inc. | G93: Indianapolis, IN | H93: ALF/SNF w/ villa | I93: 12 villa | M93: Not stated | N93: Transportation | P93: One meal per day | Q93: Bi-weekly Housekeeping | S93: Emergency call system | U93: Utilities (electricity, gas, water, sewer, trash); taxes | W93: Attached one- and two-car garage | Z93: 1975 | AA93: Included | AB93: Not stated | AC93: Included | AD93: Included | AE93: Not stated | AF93: Included | AG93: Not stated | AH93: Included | AI93: Not stated
A94: 93 | B94: Laura Lopez | C94: Word doc: Villa Study Scratch List (Updated Oct 2023) | D94: Oct 2023 (doc); received by email Sept 2026 | E94: Beech Grove Meadows | F94: American Senior Communities | G94: Beech Grove, IN | H94: ALF/SNF w/ villas | I94: 35 villas | J94: Garden Homes starting at $1323 | K94: 1323 | L94: 1323 | M94: Not stated | N94: Transportation | U94: “All utilities included except telephone” | W94: Attached garage | Z94: 1952 | AA94: Included | AB94: Not stated | AC94: Not stated | AD94: Not stated | AE94: Not stated | AF94: Not stated | AG94: Not stated | AH94: Included | AI94: Not stated
A95: 94 | B95: Laura Lopez | C95: Word doc: Villa Study Scratch List (Updated Oct 2023) | D95: Oct 2023 (doc); received by email Sept 2026 | E95: Ohio Living Breckenridge Village | F95: Ohio Living | G95: Willoughby, OH | H95: Entry Fee CCRC | I95: 75 villas (1375 – 2000 sq ft) | M95: Yes | N95: Transportation | S95: Emergency system | U95: Basic Cable; Property tax, insurance, water, and sewer | W95: Attached 1-, 1 ½-, and 2-car garages | Y95: Danbury Chardon, OH | Z95: 1923 | AA95: Included | AB95: Not stated | AC95: Not stated | AD95: Not stated | AE95: Not stated | AF95: Included | AG95: Not stated | AH95: Included | AI95: Not stated
A96: 95 | B96: Laura Lopez | C96: Word doc: Villa Study Scratch List (Updated Oct 2023) | D96: Oct 2023 (doc); received by email Sept 2026 | E96: Vitalia Mentor | F96: Arrow Senior Living | G96: Mentor, OH | H96: rental-only continuum | I96: 59 villas (1191 – 1371 sq ft) | M96: Not stated | T96: Interior/exterior maintenance | W96: Attached garage; Covered patio | Y96: Danbury Chardon, OH | Z96: 2023 | AA96: Not stated | AB96: Not stated | AC96: Not stated | AD96: Not stated | AE96: Not stated | AF96: Not stated | AG96: Included | AH96: Not stated | AI96: Not stated
A97: 96 | B97: Laura Lopez | C97: Word doc: Villa Study Scratch List (Updated Oct 2023) | D97: Oct 2023 (doc); received by email Sept 2026 | E97: The Cottages at Allen Springs | F97: Covenant Developments | G97: Jenison, MI | H97: villas | I97: 61 villas | M97: Not stated | S97: Emergency call system | U97: Gas, electric, property taxes, city water, sewer, cable, and internet | V97: Priority access to American House Jenison | W97: In-unit washer/dryer; Attached garages | X97: Considered a comp? | AA97: Not stated | AB97: Not stated | AC97: Not stated | AD97: Not stated | AE97: Not stated | AF97: Included | AG97: Not stated | AH97: Included | AI97: Included
A98: 97 | B98: Laura Lopez | C98: Word doc: Villa Study Scratch List (Updated Oct 2023) | D98: Oct 2023 (doc); received by email Sept 2026 | E98: Marian Village | F98: Franciscan Ministries | G98: Homer Glen, IL | H98: Entrance Fee CCRC | I98: 72 villas (1126 – 1300 sq ft) | M98: Yes | N98: Transportation | W98: Attached garage; In-unit washer/dryer | Y98: Romeoville IL Acquisition, Jan 2022 | Z98: 1998 | AA98: Included | AB98: Not stated | AC98: Not stated | AD98: Not stated | AE98: Not stated | AF98: Not stated | AG98: Not stated | AH98: Not stated | AI98: Not stated
A99: 98 | B99: Laura Lopez | C99: Word doc: Villa Study Scratch List (Updated Oct 2023) | D99: Oct 2023 (doc); received by email Sept 2026 | E99: Rose Senior Living Avon | F99: Life Care Services | G99: Avon, OH | H99: rental-only continuum | I99: 76 villas (966 – 1404 sq ft) | J99: One Bed/One Bath: $2385 | Two Bed/Two Bath: $2985 | Two Bed/Two Bath + den: $3480 | K99: 2385 | L99: 3480 | M99: Not stated | W99: Attached two-car garage; In-unit washer/dryer; Screened patio | Y99: Rocky River, OH – Fall 2021 | Z99: 2019 | AA99: Not stated | AB99: Not stated | AC99: Not stated | AD99: Not stated | AE99: Not stated | AF99: Not stated | AG99: Not stated | AH99: Not stated | AI99: Not stated
A100: 99 | B100: Laura Lopez | C100: Word doc: Villa Study Scratch List (Updated Oct 2023) | D100: Oct 2023 (doc); received by email Sept 2026 | E100: Sprenger Health Care Towne Center | G100: Avon Lake, OH | H100: ?) (Rental-only continuum | I100: 100ish villas | M100: Not stated | X100: No mention of villas on website or NIC Maps | AA100: Not stated | AB100: Not stated | AC100: Not stated | AD100: Not stated | AE100: Not stated | AF100: Not stated | AG100: Not stated | AH100: Not stated | AI100: Not stated
...

Sheet Synthesis
A1: Synthesis — Cottage / Villa Service Offerings Across Four Sources
A2: All counts below are live formulas over the Consolidated Data tab (tier columns). Narrative cells summarize what each source reported.
A4: 1. Service coverage by function — how often each function is reported
A5: Function | B5: Source | C5: n (rows) | D5: Included | E5: Included (limited) | F5: Available (extra cost) | G5: Not provided | H5: Not stated | I5: Any mention | J5: % any mention | K5: % included (of mentions)
A6: Transportation | B6: Laura Lopez | C6: =COUNTIF('Consolidated Data'!$B$2:$B$231,"Laura Lopez") -> 215 | D6: =COUNTIFS('Consolidated Data'!$B$2:$B$231,"Laura Lopez",'Consolidated Data'!$AA$2:$AA$231,"Included") -> 55 | E6: =COUNTIFS('Consolidated Data'!$B$2:$B$231,"Laura Lopez",'Consolidated Data'!$AA$2:$AA$231,"Included (limited)") -> 0 | F6: =COUNTIFS('Consolidated Data'!$B$2:$B$231,"Laura Lopez",'Consolidated Data'!$AA$2:$AA$231,"Available (extra cost)") -> 0 | G6: =COUNTIFS('Consolidated Data'!$B$2:$B$231,"Laura Lopez",'Consolidated Data'!$AA$2:$AA$231,"Not provided") -> 0 | H6: =COUNTIFS('Consolidated Data'!$B$2:$B$231,"Laura Lopez",'Consolidated Data'!$AA$2:$AA$231,"Not stated") -> 160 | I6: =C6-H6 -> 55 | J6: =IF(C6=0,0,I6/C6) -> 0.25581395 | K6: =IF(I6=0,0,(D6+E6)/I6) -> 1
A7: Transportation | B7: Jennifer Saxman | C7: =COUNTIF('Consolidated Data'!$B$2:$B$231,"Jennifer Saxman") -> 11 | D7: =COUNTIFS('Consolidated Data'!$B$2:$B$231,"Jennifer Saxman",'Consolidated Data'!$AA$2:$AA$231,"Included") -> 7 | E7: =COUNTIFS('Consolidated Data'!$B$2:$B$231,"Jennifer Saxman",'Consolidated Data'!$AA$2:$AA$231,"Included (limited)") -> 0 | F7: =COUNTIFS('Consolidated Data'!$B$2:$B$231,"Jennifer Saxman",'Consolidated Data'!$AA$2:$AA$231,"Available (extra cost)") -> 3 | G7: =COUNTIFS('Consolidated Data'!$B$2:$B$231,"Jennifer Saxman",'Consolidated Data'!$AA$2:$AA$231,"Not provided") -> 1 | H7: =COUNTIFS('Consolidated Data'!$B$2:$B$231,"Jennifer Saxman",'Consolidated Data'!$AA$2:$AA$231,"Not stated") -> 0 | I7: =C7-H7 -> 11 | J7: =IF(C7=0,0,I7/C7) -> 1 | K7: =IF(I7=0,0,(D7+E7)/I7) -> 0.63636364
A8: Life Enrichment / Campus Amenities | B8: Laura Lopez | C8: =COUNTIF('Consolidated Data'!$B$2:$B$231,"Laura Lopez") -> 215 | D8: =COUNTIFS('Consolidated Data'!$B$2:$B$231,"Laura Lopez",'Consolidated Data'!$AB$2:$AB$231,"Included") -> 52 | E8: =COUNTIFS('Consolidated Data'!$B$2:$B$231,"Laura Lopez",'Consolidated Data'!$AB$2:$AB$231,"Included (limited)") -> 0 | F8: =COUNTIFS('Consolidated Data'!$B$2:$B$231,"Laura Lopez",'Consolidated Data'!$AB$2:$AB$231,"Available (extra cost)") -> 2 | G8: =COUNTIFS('Consolidated Data'!$B$2:$B$231,"Laura Lopez",'Consolidated Data'!$AB$2:$AB$231,"Not provided") -> 0 | H8: =COUNTIFS('Consolidated Data'!$B$2:$B$231,"Laura Lopez",'Consolidated Data'!$AB$2:$AB$231,"Not stated") -> 161 | I8: =C8-H8 -> 54 | J8: =IF(C8=0,0,I8/C8) -> 0.25116279 | K8: =IF(I8=0,0,(D8+E8)/I8) -> 0.96296296
A9: Life Enrichment / Campus Amenities | B9: Jennifer Saxman | C9: =COUNTIF('Consolidated Data'!$B$2:$B$231,"Jennifer Saxman") -> 11 | D9: =COUNTIFS('Consolidated Data'!$B$2:$B$231,"Jennifer Saxman",'Consolidated Data'!$AB$2:$AB$231,"Included") -> 7 | E9: =COUNTIFS('Consolidated Data'!$B$2:$B$231,"Jennifer Saxman",'Consolidated Data'!$AB$2:$AB$231,"Included (limited)") -> 1 | F9: =COUNTIFS('Consolidated Data'!$B$2:$B$231,"Jennifer Saxman",'Consolidated Data'!$AB$2:$AB$231,"Available (extra cost)") -> 3 | G9: =COUNTIFS('Consolidated Data'!$B$2:$B$231,"Jennifer Saxman",'Consolidated Data'!$AB$2:$AB$231,"Not provided") -> 0 | H9: =COUNTIFS('Consolidated Data'!$B$2:$B$231,"Jennifer Saxman",'Consolidated Data'!$AB$2:$AB$231,"Not stated") -> 0 | I9: =C9-H9 -> 11 | J9: =IF(C9=0,0,I9/C9) -> 1 | K9: =IF(I9=0,0,(D9+E9)/I9) -> 0.72727273
A10: Culinary / Dining | B10: Laura Lopez | C10: =COUNTIF('Consolidated Data'!$B$2:$B$231,"Laura Lopez") -> 215 | D10: =COUNTIFS('Consolidated Data'!$B$2:$B$231,"Laura Lopez",'Consolidated Data'!$AC$2:$AC$231,"Included") -> 36 | E10: =COUNTIFS('Consolidated Data'!$B$2:$B$231,"Laura Lopez",'Consolidated Data'!$AC$2:$AC$231,"Included (limited)") -> 0 | F10: =COUNTIFS('Consolidated Data'!$B$2:$B$231,"Laura Lopez",'Consolidated Data'!$AC$2:$AC$231,"Available (extra cost)") -> 17 | G10: =COUNTIFS('Consolidated Data'!$B$2:$B$231,"Laura Lopez",'Consolidated Data'!$AC$2:$AC$231,"Not provided") -> 0 | H10: =COUNTIFS('Consolidated Data'!$B$2:$B$231,"Laura Lopez",'Consolidated Data'!$AC$2:$AC$231,"Not stated") -> 162 | I10: =C10-H10 -> 53 | J10: =IF(C10=0,0,I10/C10) -> 0.24651163 | K10: =IF(I10=0,0,(D10+E10)/I10) -> 0.67924528
A11: Culinary / Dining | B11: Jennifer Saxman | C11: =COUNTIF('Consolidated Data'!$B$2:$B$231,"Jennifer Saxman") -> 11 | D11: =COUNTIFS('Consolidated Data'!$B$2:$B$231,"Jennifer Saxman",'Consolidated Data'!$AC$2:$AC$231,"Included") -> 3 | E11: =COUNTIFS('Consolidated Data'!$B$2:$B$231,"Jennifer Saxman",'Consolidated Data'!$AC$2:$AC$231,"Included (limited)") -> 0 | F11: =COUNTIFS('Consolidated Data'!$B$2:$B$231,"Jennifer Saxman",'Consolidated Data'!$AC$2:$AC$231,"Available (extra cost)") -> 7 | G11: =COUNTIFS('Consolidated Data'!$B$2:$B$231,"Jennifer Saxman",'Consolidated Data'!$AC$2:$AC$231,"Not provided") -> 1 | H11: =COUNTIFS('Consolidated Data'!$B$2:$B$231,"Jennifer Saxman",'Consolidated Data'!$AC$2:$AC$231,"Not stated") -> 0 | I11: =C11-H11 -> 11 | J11: =IF(C11=0,0,I11/C11) -> 1 | K11: =IF(I11=0,0,(D11+E11)/I11) -> 0.27272727
A12: Housekeeping / Laundry & Linen | B12: Laura Lopez | C12: =COUNTIF('Consolidated Data'!$B$2:$B$231,"Laura Lopez") -> 215 | D12: =COUNTIFS('Consolidated Data'!$B$2:$B$231,"Laura Lopez",'Consolidated Data'!$AD$2:$AD$231,"Included") -> 60 | E12: =COUNTIFS('Consolidated Data'!$B$2:$B$231,"Laura Lopez",'Consolidated Data'!$AD$2:$AD$231,"Included (limited)") -> 0 | F12: =COUNTIFS('Consolidated Data'!$B$2:$B$231,"Laura Lopez",'Consolidated Data'!$AD$2:$AD$231,"Available (extra cost)") -> 9 | G12: =COUNTIFS('Consolidated Data'!$B$2:$B$231,"Laura Lopez",'Consolidated Data'!$AD$2:$AD$231,"Not provided") -> 0 | H12: =COUNTIFS('Consolidated Data'!$B$2:$B$231,"Laura Lopez",'Consolidated Data'!$AD$2:$AD$231,"Not stated") -> 146 | I12: =C12-H12 -> 69 | J12: =IF(C12=0,0,I12/C12) -> 0.32093023 | K12: =IF(I12=0,0,(D12+E12)/I12) -> 0.86956522
A13: Housekeeping / Laundry & Linen | B13: Jennifer Saxman | C13: =COUNTIF('Consolidated Data'!$B$2:$B$231,"Jennifer Saxman") -> 11 | D13: =COUNTIFS('Consolidated Data'!$B$2:$B$231,"Jennifer Saxman",'Consolidated Data'!$AD$2:$AD$231,"Included") -> 6 | E13: =COUNTIFS('Consolidated Data'!$B$2:$B$231,"Jennifer Saxman",'Consolidated Data'!$AD$2:$AD$231,"Included (limited)") -> 0 | F13: =COUNTIFS('Consolidated Data'!$B$2:$B$231,"Jennifer Saxman",'Consolidated Data'!$AD$2:$AD$231,"Available (extra cost)") -> 5 | G13: =COUNTIFS('Consolidated Data'!$B$2:$B$231,"Jennifer Saxman",'Consolidated Data'!$AD$2:$AD$231,"Not provided") -> 0 | H13: =COUNTIFS('Consolidated Data'!$B$2:$B$231,"Jennifer Saxman",'Consolidated Data'!$AD$2:$AD$231,"Not stated") -> 0 | I13: =C13-H13 -> 11 | J13: =IF(C13=0,0,I13/C13) -> 1 | K13: =IF(I13=0,0,(D13+E13)/I13) -> 0.54545455
A14: Wellness / Fitness / Health | B14: Laura Lopez | C14: =COUNTIF('Consolidated Data'!$B$2:$B$231,"Laura Lopez") -> 215 | D14: =COUNTIFS('Consolidated Data'!$B$2:$B$231,"Laura Lopez",'Consolidated Data'!$AE$2:$AE$231,"Included") -> 48 | E14: =COUNTIFS('Consolidated Data'!$B$2:$B$231,"Laura Lopez",'Consolidated Data'!$AE$2:$AE$231,"Included (limited)") -> 0 | F14: =COUNTIFS('Consolidated Data'!$B$2:$B$231,"Laura Lopez",'Consolidated Data'!$AE$2:$AE$231,"Available (extra cost)") -> 12 | G14: =COUNTIFS('Consolidated Data'!$B$2:$B$231,"Laura Lopez",'Consolidated Data'!$AE$2:$AE$231,"Not provided") -> 0 | H14: =COUNTIFS('Consolidated Data'!$B$2:$B$231,"Laura Lopez",'Consolidated Data'!$AE$2:$AE$231,"Not stated") -> 155 | I14: =C14-H14 -> 60 | J14: =IF(C14=0,0,I14/C14) -> 0.27906977 | K14: =IF(I14=0,0,(D14+E14)/I14) -> 0.8
A15: Wellness / Fitness / Health | B15: Jennifer Saxman | C15: =COUNTIF('Consolidated Data'!$B$2:$B$231,"Jennifer Saxman") -> 11 | D15: =COUNTIFS('Consolidated Data'!$B$2:$B$231,"Jennifer Saxman",'Consolidated Data'!$AE$2:$AE$231,"Included") -> 7 | E15: =COUNTIFS('Consolidated Data'!$B$2:$B$231,"Jennifer Saxman",'Consolidated Data'!$AE$2:$AE$231,"Included (limited)") -> 1 | F15: =COUNTIFS('Consolidated Data'!$B$2:$B$231,"Jennifer Saxman",'Consolidated Data'!$AE$2:$AE$231,"Available (extra cost)") -> 3 | G15: =COUNTIFS('Consolidated Data'!$B$2:$B$231,"Jennifer Saxman",'Consolidated Data'!$AE$2:$AE$231,"Not provided") -> 0 | H15: =COUNTIFS('Consolidated Data'!$B$2:$B$231,"Jennifer Saxman",'Consolidated Data'!$AE$2:$AE$231,"Not stated") -> 0 | I15: =C15-H15 -> 11 | J15: =IF(C15=0,0,I15/C15) -> 1 | K15: =IF(I15=0,0,(D15+E15)/I15) -> 0.72727273
A16: Emergency / Safety / Security | B16: Laura Lopez | C16: =COUNTIF('Consolidated Data'!$B$2:$B$231,"Laura Lopez") -> 215 | D16: =COUNTIFS('Consolidated Data'!$B$2:$B$231,"Laura Lopez",'Consolidated Data'!$AF$2:$AF$231,"Included") -> 74 | E16: =COUNTIFS('Consolidated Data'!$B$2:$B$231,"Laura Lopez",'Consolidated Data'!$AF$2:$AF$231,"Included (limited)") -> 0 | F16: =COUNTIFS('Consolidated Data'!$B$2:$B$231,"Laura Lopez",'Consolidated Data'!$AF$2:$AF$231,"Available (extra cost)") -> 2 | G16: =COUNTIFS('Consolidated Data'!$B$2:$B$231,"Laura Lopez",'Consolidated Data'!$AF$2:$AF$231,"Not provided") -> 0 | H16: =COUNTIFS('Consolidated Data'!$B$2:$B$231,"Laura Lopez",'Consolidated Data'!$AF$2:$AF$231,"Not stated") -> 139 | I16: =C16-H16 -> 76 | J16: =IF(C16=0,0,I16/C16) -> 0.35348837 | K16: =IF(I16=0,0,(D16+E16)/I16) -> 0.97368421
A17: Emergency / Safety / Security | B17: Jennifer Saxman | C17: =COUNTIF('Consolidated Data'!$B$2:$B$231,"Jennifer Saxman") -> 11 | D17: =COUNTIFS('Consolidated Data'!$B$2:$B$231,"Jennifer Saxman",'Consolidated Data'!$AF$2:$AF$231,"Included") -> 9 | E17: =COUNTIFS('Consolidated Data'!$B$2:$B$231,"Jennifer Saxman",'Consolidated Data'!$AF$2:$AF$231,"Included (limited)") -> 0 | F17: =COUNTIFS('Consolidated Data'!$B$2:$B$231,"Jennifer Saxman",'Consolidated Data'!$AF$2:$AF$231,"Available (extra cost)") -> 2 | G17: =COUNTIFS('Consolidated Data'!$B$2:$B$231,"Jennifer Saxman",'Consolidated Data'!$AF$2:$AF$231,"Not provided") -> 0 | H17: =COUNTIFS('Consolidated Data'!$B$2:$B$231,"Jennifer Saxman",'Consolidated Data'!$AF$2:$AF$231,"Not stated") -> 0 | I17: =C17-H17 -> 11 | J17: =IF(C17=0,0,I17/C17) -> 1 | K17: =IF(I17=0,0,(D17+E17)/I17) -> 0.81818182
A18: Maintenance (Interior / Exterior / Grounds) | B18: Laura Lopez | C18: =COUNTIF('Consolidated Data'!$B$2:$B$231,"Laura Lopez") -> 215 | D18: =COUNTIFS('Consolidated Data'!$B$2:$B$231,"Laura Lopez",'Consolidated Data'!$AG$2:$AG$231,"Included") -> 102 | E18: =COUNTIFS('Consolidated Data'!$B$2:$B$231,"Laura Lopez",'Consolidated Data'!$AG$2:$AG$231,"Included (limited)") -> 0 | F18: =COUNTIFS('Consolidated Data'!$B$2:$B$231,"Laura Lopez",'Consolidated Data'!$AG$2:$AG$231,"Available (extra cost)") -> 1 | G18: =COUNTIFS('Consolidated Data'!$B$2:$B$231,"Laura Lopez",'Consolidated Data'!$AG$2:$AG$231,"Not provided") -> 0 | H18: =COUNTIFS('Consolidated Data'!$B$2:$B$231,"Laura Lopez",'Consolidated Data'!$AG$2:$AG$231,"Not stated") -> 112 | I18: =C18-H18 -> 103 | J18: =IF(C18=0,0,I18/C18) -> 0.47906977 | K18: =IF(I18=0,0,(D18+E18)/I18) -> 0.99029126
A19: Maintenance (Interior / Exterior / Grounds) | B19: Jennifer Saxman | C19: =COUNTIF('Consolidated Data'!$B$2:$B$231,"Jennifer Saxman") -> 11 | D19: =COUNTIFS('Consolidated Data'!$B$2:$B$231,"Jennifer Saxman",'Consolidated Data'!$AG$2:$AG$231,"Included") -> 11 | E19: =COUNTIFS('Consolidated Data'!$B$2:$B$231,"Jennifer Saxman",'Consolidated Data'!$AG$2:$AG$231,"Included (limited)") -> 0 | F19: =COUNTIFS('Consolidated Data'!$B$2:$B$231,"Jennifer Saxman",'Consolidated Data'!$AG$2:$AG$231,"Available (extra cost)") -> 0 | G19: =COUNTIFS('Consolidated Data'!$B$2:$B$231,"Jennifer Saxman",'Consolidated Data'!$AG$2:$AG$231,"Not provided") -> 0 | H19: =COUNTIFS('Consolidated Data'!$B$2:$B$231,"Jennifer Saxman",'Consolidated Data'!$AG$2:$AG$231,"Not stated") -> 0 | I19: =C19-H19 -> 11 | J19: =IF(C19=0,0,I19/C19) -> 1 | K19: =IF(I19=0,0,(D19+E19)/I19) -> 1
A20: Utilities / Taxes / Insurance | B20: Laura Lopez | C20: =COUNTIF('Consolidated Data'!$B$2:$B$231,"Laura Lopez") -> 215 | D20: =COUNTIFS('Consolidated Data'!$B$2:$B$231,"Laura Lopez",'Consolidated Data'!$AH$2:$AH$231,"Included") -> 118 | E20: =COUNTIFS('Consolidated Data'!$B$2:$B$231,"Laura Lopez",'Consolidated Data'!$AH$2:$AH$231,"Included (limited)") -> 0 | F20: =COUNTIFS('Consolidated Data'!$B$2:$B$231,"Laura Lopez",'Consolidated Data'!$AH$2:$AH$231,"Available (extra cost)") -> 2 | G20: =COUNTIFS('Consolidated Data'!$B$2:$B$231,"Laura Lopez",'Consolidated Data'!$AH$2:$AH$231,"Not provided") -> 0 | H20: =COUNTIFS('Consolidated Data'!$B$2:$B$231,"Laura Lopez",'Consolidated Data'!$AH$2:$AH$231,"Not stated") -> 95 | I20: =C20-H20 -> 120 | J20: =IF(C20=0,0,I20/C20) -> 0.55813953 | K20: =IF(I20=0,0,(D20+E20)/I20) -> 0.98333333
A21: Utilities / Taxes / Insurance | B21: Jennifer Saxman | C21: =COUNTIF('Consolidated Data'!$B$2:$B$231,"Jennifer Saxman") -> 11 | D21: =COUNTIFS('Consolidated Data'!$B$2:$B$231,"Jennifer Saxman",'Consolidated Data'!$AH$2:$AH$231,"Included") -> 11 | E21: =COUNTIFS('Consolidated Data'!$B$2:$B$231,"Jennifer Saxman",'Consolidated Data'!$AH$2:$AH$231,"Included (limited)") -> 0 | F21: =COUNTIFS('Consolidated Data'!$B$2:$B$231,"Jennifer Saxman",'Consolidated Data'!$AH$2:$AH$231,"Available (extra cost)") -> 0 | G21: =COUNTIFS('Consolidated Data'!$B$2:$B$231,"Jennifer Saxman",'Consolidated Data'!$AH$2:$AH$231,"Not provided") -> 0 | H21: =COUNTIFS('Consolidated Data'!$B$2:$B$231,"Jennifer Saxman",'Consolidated Data'!$AH$2:$AH$231,"Not stated") -> 0 | I21: =C21-H21 -> 11 | J21: =IF(C21=0,0,I21/C21) -> 1 | K21: =IF(I21=0,0,(D21+E21)/I21) -> 1
A22: Additional / À La Carte / Concierge | B22: Laura Lopez | C22: =COUNTIF('Consolidated Data'!$B$2:$B$231,"Laura Lopez") -> 215 | D22: =COUNTIFS('Consolidated Data'!$B$2:$B$231,"Laura Lopez",'Consolidated Data'!$AI$2:$AI$231,"Included") -> 10 | E22: =COUNTIFS('Consolidated Data'!$B$2:$B$231,"Laura Lopez",'Consolidated Data'!$AI$2:$AI$231,"Included (limited)") -> 0 | F22: =COUNTIFS('Consolidated Data'!$B$2:$B$231,"Laura Lopez",'Consolidated Data'!$AI$2:$AI$231,"Available (extra cost)") -> 4 | G22: =COUNTIFS('Consolidated Data'!$B$2:$B$231,"Laura Lopez",'Consolidated Data'!$AI$2:$AI$231,"Not provided") -> 0 | H22: =COUNTIFS('Consolidated Data'!$B$2:$B$231,"Laura Lopez",'Consolidated Data'!$AI$2:$AI$231,"Not stated") -> 201 | I22: =C22-H22 -> 14 | J22: =IF(C22=0,0,I22/C22) -> 0.065116279 | K22: =IF(I22=0,0,(D22+E22)/I22) -> 0.71428571
A23: Additional / À La Carte / Concierge | B23: Jennifer Saxman | C23: =COUNTIF('Consolidated Data'!$B$2:$B$231,"Jennifer Saxman") -> 11 | D23: =COUNTIFS('Consolidated Data'!$B$2:$B$231,"Jennifer Saxman",'Consolidated Data'!$AI$2:$AI$231,"Included") -> 5 | E23: =COUNTIFS('Consolidated Data'!$B$2:$B$231,"Jennifer Saxman",'Consolidated Data'!$AI$2:$AI$231,"Included (limited)") -> 1 | F23: =COUNTIFS('Consolidated Data'!$B$2:$B$231,"Jennifer Saxman",'Consolidated Data'!$AI$2:$AI$231,"Available (extra cost)") -> 5 | G23: =COUNTIFS('Consolidated Data'!$B$2:$B$231,"Jennifer Saxman",'Consolidated Data'!$AI$2:$AI$231,"Not provided") -> 0 | H23: =COUNTIFS('Consolidated Data'!$B$2:$B$231,"Jennifer Saxman",'Consolidated Data'!$AI$2:$AI$231,"Not stated") -> 0 | I23: =C23-H23 -> 11 | J23: =IF(C23=0,0,I23/C23) -> 1 | K23: =IF(I23=0,0,(D23+E23)/I23) -> 0.54545455
A24: Reading note: Lopez rows are a web-researched inventory (Oct 2023) where "Not stated" usually means the community website did not list that service, not that it is absent. Saxman rows include the 6-community table plus narrative examples. Witzgall (2 model rows) and Wood (2 rows) are excluded from counts because they are not community-level inventories.
A26: 2. Pricing snapshot
A27: Metric | B27: Value | C27: Source / basis
A28: Lopez: communities with a monthly fee reported | B28: =COUNTIFS('Consolidated Data'!$B$2:$B$231,"Laura Lopez",'Consolidated Data'!$K$2:$K$231,">0") -> 54 | C28: Consolidated Data col K (parsed from reported pricing)
A29: Lopez: lowest reported monthly fee | B29: =MIN('Consolidated Data'!$K$2:$K$216) -> 515 | C29: see note
A30: Lopez: median reported monthly fee (low end of each range) | B30: =MEDIAN('Consolidated Data'!$K$2:$K$216) -> 2799.5 | C30: Consolidated Data col K, Lopez rows only
A31: Lopez: highest reported monthly fee | B31: =MAX('Consolidated Data'!$L$2:$L$216) -> 6900 | C31: Consolidated Data col L, Lopez rows only
A32: Lopez: communities confirmed to require an entry / entrance fee | B32: =COUNTIFS('Consolidated Data'!$B$2:$B$231,"Laura Lopez",'Consolidated Data'!$M$2:$M$231,"Yes") -> 63 | C32: Consolidated Data col M
A33: Lopez: additional CCRCs where entry fee not stated | B33: =COUNTIFS('Consolidated Data'!$B$2:$B$231,"Laura Lopez",'Consolidated Data'!$M$2:$M$231,"CCRC (entry fee not stated)") -> 35 | C33: Consolidated Data col M
A34: Witzgall: typical rental cottage monthly fee | B34: $2,500 – $6,500+ per month | C34: Witzgall PDF, fee table (rental model; 900 – 1,800+ sq ft)
A35: Witzgall: one-time move-in / community fee | B35: $1,000 – $5,000 (non-refundable) | C35: Witzgall PDF
A36: Witzgall: second-person fee | B36: $500 – $1,000 per month | C36: Witzgall PDF
A37: Witzgall: rental cottage premium vs. IL apartment | B37: 15% – 30% monthly premium over IL apartments of similar size ($2,200 – $4,500/mo) | C37: Witzgall PDF, strategic takeaways
A38: Witzgall: dining upgrade to 3 meals/day | B38: $600 – $900 per month | C38: Witzgall PDF
A39: Witzgall: weekly housekeeping upgrade | B39: +$150 – $300 per month over bi-weekly base | C39: Witzgall PDF
A40: Saxman: optional housekeeping (Highgrove at Tates Creek) | B40: approx. $240 per month | C40: Saxman email
A41: Lopez: à la carte housekeeping (Legacy Living Florence) | B41: $25 per hour | C41: Lopez inventory
A42: Note: Lopez min/median/max ranges reference rows 2–216 of Consolidated Data, which are exactly the Lopez rows (Witzgall, Wood and Saxman rows follow). Lopez monthly fees mix rental rates and CCRC monthly service fees that sit on top of an entrance fee (e.g., Wesley Manor $515/mo with a $179K entrance fee), so the low end understates rental-equivalent cost.
A44: 3. What each source says, by function
A45: Function | B45: Laura Lopez — inventory of ~215 villa/cottage products (Midwest + TN/KY/OK) | C45: Ken Witzgall — rental cottage model profile | D45: Scott Wood — two operators | E45: Jennifer Saxman — detached cottage benchmarking | F45: Cross-source synthesis
A46: Transportation | B46: Listed at roughly a quarter of communities, and always as included when listed (scheduled community transportation). Never priced separately in the inventory. | C46: Included: scheduled group shuttles (shopping, banking) and medical transport within a 10-mile radius. Extras: beyond 10 miles ($2.50–$4.00/mile or $25–$50/trip), private car service ($30–$60/hr), airport runs ($75–$150). | D46: Provincial/Discovery: same as community residents, 10-mile radius. Integrated Senior Living: not provided. | E46: "Fairly common." 5 of 6 table communities include scheduled transportation or routine outings; Our Lady of Angels does not provide it. Unscheduled transportation appears as an à la carte item (Hamilton Trace). | F46: Scheduled/group transportation inside a ~10-mile radius is the norm and is treated as a base inclusion wherever cottage residents share the main campus. Personal or on-demand transportation is consistently an add-on. The 10-mile radius shows up independently in Witzgall and Wood.
A47: Life Enrichment / Campus Amenities | B47: About a quarter of communities explicitly list campus amenity access (fitness, pool, chapel, theater, bistro, woodshop, etc.); when listed it is included. Newer rental products (Vitalia, Traditions) lean on clubhouse-style amenities. | C47: Included: on-campus classes/lectures, fitness center and pool access, social clubs and events. Extras: excursion tickets at cost, workshop materials ($10–$30), personal training ($60–$90/hr). | D47: Both operators: same as community residents. | E47: Programming is "fairly common"; all 6 table communities offer community activities/programming, ranging from "limited" (Our Lady of Angels) to fitness/pool/community programming (Wesley Village). | F47: Full access to the main community's programming and amenities is a universal, low-marginal-cost inclusion. Differentiation happens on outings, specialty classes and personal training, which are pay-per-use everywhere they are itemized.
A48: Culinary / Dining | B48: Only ~25% mention dining; roughly a third of those are optional or credit-based ("flexible meal allowance," "$490/$540/$600 monthly dining credit," "meal options available"). Included plans range from continental breakfast to 1 meal/day, 10–30 meals/month, or 3 meals/day (rare, usually AL-adjacent). | C48: Included: continental breakfast OR 1 chef-prepared meal/day, or a $300/month declining-balance card. Extras: 3-meal plan upgrade ($600–$900/mo), guest meals ($15–$25), villa delivery ($5–$10/meal). | D48: Provincial/Discovery: two meals included. Integrated Senior Living: 1 meal included, rest à la carte. | E48: "Varies considerably" and often optional/extra. Table spans meals not provided (Our Lady of Angels) → breakfast only (Wesley Village) → 15 meals/month (Robin Run) → breakfast plus one dinner weekly (Cedarhurst). | F48: Dining is the most variable function and the clearest place to tier. Cottages have full kitchens, so the market converges on a light base (breakfast or a modest declining-balance credit) with upgrade plans priced separately. Full meal plans belong at the top tier only.
A49: Housekeeping / Laundry & Linen | B49: About a third mention housekeeping. Bi-weekly is the most common cadence, then weekly (often paired with flat-linen service, e.g., Five Star, Concordia OKC, Zarrow Pointe), then monthly "light" housekeeping (Twin Lakes/Twin Towers). Laundry service is occasionally included or "available." | C49: Included: bi-weekly light interior housekeeping. Extras: weekly upgrade (+$150–$300/mo), deep cleaning ($40–$60/hr), laundry & linen ($20–$35/load or $100–$150/mo). | D49: Provincial/Discovery: weekly housekeeping. Integrated Senior Living: not provided. | E49: "Varies considerably." Every other week (Cedarhurst, Hamilton Trace), monthly (Robin Run, Garbry Ridge), included (Our Lady of Angels), or optional (~$240/mo at Highgrove; optional at Bay Ridge/Swanhaven). | F49: Bi-weekly housekeeping is the market midpoint; monthly or optional at the light end, weekly plus linen at the premium end. Housekeeping is the one service with a consistent, quotable upcharge across sources ($150–$300/mo for weekly; ~$240/mo when sold stand-alone).
A50: Wellness / Fitness / Health | B50: Rarely listed as a cottage-specific service; appears mostly as campus fitness/pool/wellness center access, on-site clinic or rehab "available," an annual health/wellness allowance (Twin Lakes), or free health-center days (Village at Germantown). | C50: Included: monthly wellness check-up (BP, weight). Extras: medication management ($300–$600/mo), PT/OT copays, replacement pendant ($100–$150). | D50: Both operators reported N/A. | E50: "Fairly common." Wellness programming or a monthly wellness clinic at 5 of 6; "limited" at Our Lady of Angels. | F50: Wellness is under-defined for cottages. The defensible base is campus fitness access plus a light-touch wellness clinic; clinical or care services (medication management, home health, therapy) are universally à la carte or third-party.
A51: Emergency / Safety / Security | B51: The most frequently listed service after utilities and maintenance (~35%): emergency call/response systems or pendants, often with 24-hour security or gated entry at CCRCs. | C51: Included: 24/7 wireless emergency responder system (pendant/pull cords). Extra: replacement pendant/fob. | D51: Not addressed. | E51: "Fairly common." Emergency response/call systems included at 5 of 6 communities. | F51: An emergency response system is table stakes at every tier; 24-hour security or gated entry differentiates the premium end. Cost is low and it addresses the primary anxiety of detached living.
A52: Maintenance (Interior / Exterior / Grounds) | B52: The most common inclusion (~48%): "interior/exterior maintenance," "maintenance-free living," lawn care, snow removal, landscaping, grounds. Never priced separately. | C52: Included: full exterior maintenance (lawn, snow) and routine interior appliance/utility maintenance. The "completely maintenance-free environment" is called the core value proposition. | D52: Not addressed. | E52: "Most consistently observed": lawn, landscaping, snow removal and home maintenance are removed from the resident at every example. | F52: Unanimous across sources. Removing homeownership work is the product; interior and exterior maintenance must be included at every tier and never itemized.
A53: Utilities / Taxes / Insurance | B53: Most common line item (~55%). Ranges from water/sewer/trash only, to "all utilities except phone/cable/internet," to all utilities plus cable, Wi-Fi and phone. Entry-fee CCRCs frequently add property taxes and building insurance. | C53: Standard utilities, basic cable/Wi-Fi bundled into the monthly rental fee. | D53: Not addressed. | E53: "Fairly common." Ranges from water only (Our Lady of Angels) to full gas/electric/water/sewer/trash (Garbry Ridge) and utilities plus cable and trash (Wesley Village). | F53: Water/sewer/trash is the floor; a full utility bundle with cable and Wi-Fi is the mainstream expectation for a rental product; taxes/insurance are inherent to the ownership structure rather than a service choice.
A54: Additional / À La Carte / Concierge | B54: Occasional: 24/7 concierge (Five Star, Robinwood), "concierge services" (Provision, Edgewater), homecare/laundry "available," priority access to a sister campus, $25/hr housekeeping. | C54: Pet deposit/rent, private care & support ($300–$600/mo), deep cleaning, laundry packages, guest meals, delivery fees — a deliberate ancillary revenue stream. | D54: Both operators reported N/A. | E54: Extensive menus at the better-run examples: dining, deep cleaning, pet care, carpet cleaning, handyman, home health/therapy, salon, unscheduled transportation, guest meals, laundry, concierge. Recommends a Base + Choice structure. | F54: A published à la carte menu is what separates a "better" cottage program from a "good" one. Saxman and Witzgall independently frame the same architecture: include what removes homeownership burden, sell convenience.
A56: 4. Cross-source observations
A57: • There is no single standard cottage service model (Saxman), and the Lopez inventory confirms it: 215 products range from garage-and-washer/dryer-only to fully bundled CCRC villas.
A58: • The consistent core across all four sources is the removal of homeownership work: interior/exterior maintenance, lawn, snow, landscaping, plus base utilities and an emergency response system.
A59: • Dining and housekeeping are the two functions that vary most and are most often optional or priced separately; they are therefore the natural levers for tiering.
A60: • Transportation is generally a shared-campus inclusion within a ~10-mile radius (Witzgall, Wood, Saxman); personal or on-demand transportation is an add-on.
A61: • Witzgall's fee table gives a usable price architecture for add-ons (weekly housekeeping +$150–$300/mo; 3-meal plan $600–$900/mo; laundry $100–$150/mo; care/medication support $300–$600/mo) that is consistent with Saxman's ~$240/mo optional housekeeping and Lopez's $25/hr housekeeping example.
A62: • Rental cottages command a 15–30% premium over IL apartments and lease up faster because there is no entrance fee (Witzgall); ~30% of Lopez communities require an entrance fee, typically at CCRCs.
A63: • Wood's two operators show that even within one company family, service packages diverge (two meals plus weekly housekeeping vs. one meal and no housekeeping or transportation).
A64: • Operational caveat (Witzgall): spread-footprint cottages increase staff travel time for housekeeping, maintenance and emergency response; bundled services need routing discipline to protect margin.
A65: • Cross-check: Smith Crossing appears in both Lopez (Oct 2023 web listing shows only garage, washer/dryer, porch and campus amenities) and Saxman (described as bundling housekeeping, maintenance, utilities, transportation, emergency response and wellness). Saxman's later, direct research is the more complete picture; the Lopez entry reflects what the website advertised.
A66: • Data caveats: Lopez is an Oct 2023 web scrape ("Not stated" ≠ not offered; several entries flagged "none confirmed"); Witzgall is an AI-generated market profile, not an operator disclosure; Wood and Saxman are operator/consultant reports without dates or prices for most items.

Sheet Good-Better-Best
A1: Service Offering Recommendations — Good / Better / Best by Function
A2: Three candidate offerings per function, derived from the Synthesis tab. "Good" = maintenance-free essentials (lightest viable package). "Better" = Base + Choice (market midpoint with a published add-on menu). "Best" = bundled villa experience (premium, CCRC-style inclusions). Indicative prices come from the sources cited; they are benchmarks, not a pricing recommendation.
A4: Function | B4: GOOD — Maintenance-Free Essentials | C4: BETTER — Base + Choice | D4: BEST — Bundled Villa Experience | E4: Why these three (evidence) | F4: Indicative pricing from sources | G4: Sources
A5: Transportation | B5: Scheduled group shuttle on the community's existing routes (shopping, banking, worship) within a 10-mile radius; medical appointments on set days. No personal transportation. | C5: Good, plus scheduled medical transportation within 10 miles on any weekday, and a published per-trip / per-mile rate for trips beyond 10 miles and for unscheduled rides. | D5: Better, plus a private on-demand car service allowance (e.g., a set number of personal trips per month) and after-hours / airport runs bookable through concierge. | E5: Scheduled transportation within ~10 miles is included at Provincial/Discovery (Wood), in the Witzgall model and at 5 of 6 Saxman communities; it is never itemized in the Lopez inventory. Personal/unscheduled transportation is à la carte everywhere it is mentioned (Hamilton Trace, Witzgall). | F5: Beyond-radius medical: $2.50–$4.00/mile or $25–$50/trip; private car $30–$60/hr; airport $75–$150/trip (Witzgall). | G5: Witzgall; Wood; Saxman; Lopez
A6: Life Enrichment / Campus Amenities | B6: Full access to the main community's calendar, fitness center, pool and common areas on the same basis as apartment residents. Outings and ticketed events pay-per-use. | C6: Good, plus a cottage-specific social program (neighborhood events, resident-led clubs, a cottage liaison) and a small annual outing credit. | D6: Better, plus concierge-booked excursions, specialty classes and personal training with a monthly enrichment credit, and priority registration for limited-seat events. | E6: Every source treats campus programming as an inclusion ("same as community residents" at both Wood operators; included in Witzgall; present at all 6 Saxman communities). Only excursions, materials and personal training are ever priced. | F6: Excursion tickets at cost $20–$100+; workshop materials $10–$30/class; personal training $60–$90/hr (Witzgall). | G6: Witzgall; Wood; Saxman; Lopez
A7: Culinary / Dining | B7: No meal plan in the base rent. Restaurant dining open to cottage residents at posted prices; a weekly continental breakfast or coffee social at the clubhouse. | C7: A monthly declining-balance dining credit (in the $300–$600 range) usable at any venue, with optional upgrade plans (10, 15 or 30 meals/month) priced separately and villa delivery at a per-meal fee. | D7: One chef-prepared meal per day (or 20–30 meals/month) included, plus daily continental breakfast, guest-meal allowance and villa delivery included; upgrade path to a full 3-meal plan. | E7: Dining is the most variable function: 17 of 53 Lopez mentions are optional or credit-based; Saxman ranges from none to 15 meals/month; Wood shows 1 vs 2 meals; Witzgall's base is breakfast, 1 meal/day or a $300 card. Full kitchens make a heavy plan unnecessary for most buyers. | F7: Declining-balance credits observed: $300/mo (Witzgall), $490 (Lake Forest Place), $540 (Friendship Village Dublin), $600 (The Stratford) (Lopez). 3-meal upgrade $600–$900/mo; guest meals $15–$25; delivery $5–$10/meal (Witzgall). | G7: Lopez; Witzgall; Wood; Saxman
A8: Housekeeping | B8: Not included. Housekeeping sold as a stand-alone monthly subscription or hourly service at a published rate; annual deep clean offered as an add-on. | C8: Bi-weekly light housekeeping included; weekly upgrade, deep cleaning and carpet cleaning at published prices. | D8: Weekly housekeeping with flat-linen service included, plus an annual spring deep clean; deep cleaning and organizing on request. | E8: Bi-weekly is the most common included cadence in Lopez and is the Witzgall base; monthly or optional at the light end (Robin Run, Garbry Ridge, Highgrove ~$240/mo, Integrated Senior Living none); weekly plus linen at the premium end (Five Star, Concordia OKC, Zarrow Pointe, Provincial/Discovery). | F8: Stand-alone: ~$240/mo (Saxman, Highgrove) or $25/hr (Lopez, Legacy Living Florence). Weekly upgrade over bi-weekly: +$150–$300/mo; deep clean $40–$60/hr (Witzgall). | G8: Lopez; Witzgall; Wood; Saxman
A9: Laundry & Linen | B9: In-unit washer/dryer (or hookups) provided; no laundry service. | C9: In-unit washer/dryer plus optional personal laundry and linen service priced per load or as a monthly package. | D9: In-unit washer/dryer plus weekly flat-linen service included; personal laundry package included or discounted. | E9: In-unit washer/dryer is near-universal in the Lopez inventory (a residence feature, not a service). Linen service rides with weekly housekeeping at the premium communities; laundry "available" at Trilogy campuses; Witzgall prices it as an add-on. | F9: Laundry & linen $20–$35/load or $100–$150/mo package (Witzgall). | G9: Lopez; Witzgall; Saxman
A10: Wellness / Fitness / Health | B10: Fitness center and pool access included; wellness programming on the community calendar. Clinical services referred to third parties. | C10: Good, plus a monthly on-site wellness clinic (blood pressure, weight, medication review) and an optional daily check-in call; home health and therapy providers coordinated on request at their rates. | D10: Better, plus an annual wellness/health-services allowance, a set number of free health-center days per year, and a resident wellness navigator who coordinates home care, therapy and medication management. | E10: Cottage-specific wellness is thin in Lopez (mostly campus access, occasional clinic/rehab "available", Twin Lakes annual allowance, Village at Germantown 10 free health-center days). Witzgall includes a monthly check-up and prices care services; Saxman shows wellness clinics at 5 of 6; Wood reported N/A. | F10: Medication management $300–$600/mo; PT/OT at copay; personal training $60–$90/hr (Witzgall). | G10: Lopez; Witzgall; Saxman; Wood
A11: Emergency / Safety / Security | B11: 24/7 emergency call system (pendant or pull cords) monitored by the main community; standard exterior lighting. | C11: Good, plus a wireless/mobile pendant that works across campus, 24-hour on-campus staff response and an optional daily check-in. | D11: Better, plus gated or controlled entry, 24-hour security/EMT presence, in-home smart sensors or fall detection, and priority response routing for the cottage neighborhood. | E11: Emergency response is the second most common Lopez inclusion (74 communities), included in the Witzgall base and at 5 of 6 Saxman communities. 24-hour security and gated entry appear at the CCRC/premium end (Twin Lakes, Trezevant, Kirby Pines, Holy Cross Village). Witzgall flags slower response times on spread footprints. | F11: Replacement pendant/fob $100–$150 one-time (Witzgall); no recurring charge observed in any source. | G11: Lopez; Witzgall; Saxman
A12: Maintenance (Interior / Exterior / Grounds) | B12: All exterior maintenance, lawn care, landscaping, snow and ice removal, plus repair of community-owned appliances and systems. Work-order response during business hours. | C12: Good, plus 24-hour emergency maintenance, routine interior preventive maintenance (filters, smoke detectors, seasonal checks) and a published handyman rate for resident-requested work. | D12: Better, plus included handyman hours each month, seasonal services (gutter, power-wash, window cleaning), and pre-scheduled interior refresh (paint/carpet) on a set cycle. | E12: Unanimous: maintenance is the single most common Lopez inclusion (102 communities), the Witzgall "core value proposition," and Saxman's "most consistently observed" service. It should never be optional; the tiers differ only in responsiveness and scope. | F12: Handyman appears only as an à la carte item (Cedarhurst, Saxman); no benchmark price in the sources. | G12: Lopez; Witzgall; Saxman
A13: Utilities / Taxes / Insurance | B13: Water, sewer and trash included; resident pays electric, gas, cable, internet and phone directly. | C13: All standard utilities (electric, gas, water, sewer, trash) plus basic cable and Wi-Fi bundled into the monthly fee; phone optional. | D13: Better, plus premium cable/streaming package, phone, and (for entry-fee structures) property taxes and building insurance carried by the community. | E13: Utilities are the most common Lopez line item (118 communities) and span exactly these three levels: water/sewer/trash only (Tabor Hills, Wilson Commons), all utilities plus cable/Wi-Fi (Traditions, Legacies, Oaks at Bartlett), and all utilities plus phone/cable/internet/taxes/insurance (Twin Lakes, Maple Knoll, Friendship Village Dublin). Witzgall bundles standard utilities and basic cable/Wi-Fi in rent; Saxman ranges from water-only to full bundles. | F13: Bundled inside the monthly fee in every source; no separate utility pricing reported. | G13: Lopez; Witzgall; Saxman
A14: Concierge & Convenience Services (Additional / À La Carte) | B14: Front-desk assistance during business hours; a printed price list for the few services offered (housekeeping, guest meals). | C14: A published Base + Choice menu: housekeeping upgrades, laundry, dining plans, unscheduled transportation, pet services, deep/carpet cleaning, handyman, guest meals, salon, home-health referrals, each with a posted price; billed on the monthly statement. | D14: Better, plus 24/7 concierge (package receipt, reservations, vendor coordination, travel/lock-and-leave home checks), a monthly convenience credit, and a dedicated cottage services coordinator. | E14: Saxman recommends Base + Choice explicitly and lists the fullest menus (Cedarhurst, Hamilton Trace). Witzgall structures the same items as an ancillary revenue stream. 24/7 concierge appears at Five Star and Robinwood in Lopez. Wood's operators reported nothing beyond meals, housekeeping and transport. | F14: Pet deposit $250–$500 plus $25–$50/mo; private care & support $300–$600/mo (Witzgall). Other menu items: see Housekeeping, Culinary, Transportation rows. | G14: Saxman; Witzgall; Lopez; Wood
A15: Packaging & Pricing Structure | B15: Single rental rate covering residence, maintenance, base utilities and emergency response; everything else à la carte. Positions against the lighter models (Highgrove, Bay Ridge, Swanhaven, Integrated Senior Living). | C15: Base rent plus a modest bundled service fee (bi-weekly housekeeping, full utilities, dining credit, monthly clinic) with a transparent add-on menu and a second-person fee. Positions against the Witzgall rental profile and mid-market Lopez communities. | D15: All-inclusive monthly fee (weekly housekeeping and linen, daily meal, all utilities, concierge, wellness allowance), rental or entry-fee, positioned against Smith Crossing, Five Star, The Stratford, Twin Lakes and Lake Forest Place. | E15: Witzgall: rental cottages earn a 15–30% premium over IL apartments and lease faster without an entrance fee; monthly rents $2,500–$6,500+. Lopez median reported monthly fee ≈ $2,800 with a $515–$6,900 spread. Saxman: a proactive lifestyle buyer values independence plus fewer responsibilities, so the base must feel light. | F15: Assumption for planning only: Good ≈ $2,500–$3,500/mo, Better ≈ $3,500–$5,000/mo, Best ≈ $5,000–$6,500+/mo, mapped onto the Witzgall $2,500–$6,500+ range. Move-in fee $1,000–$5,000; second person $500–$1,000/mo (Witzgall). | G15: Witzgall; Lopez; Saxman
A17: Package view — what each tier includes at a glance
A18: Element | B18: GOOD — Maintenance-Free Essentials | C18: BETTER — Base + Choice | D18: BEST — Bundled Villa Experience
A19: Always included (all tiers) | B19: Interior/exterior maintenance, lawn, snow, landscaping; water/sewer/trash; emergency call system; scheduled shuttle within ~10 miles; full campus programming and fitness access; in-unit washer/dryer; attached garage. | C19: Same | D19: Same
A20: Housekeeping | B20: À la carte only | C20: Bi-weekly included; weekly upgrade priced | D20: Weekly with linen included; annual deep clean
A21: Dining | B21: Pay as you go; weekly breakfast social | C21: Monthly dining credit; upgrade plans priced | D21: 1 meal/day (or 20–30/month) plus breakfast included
A22: Utilities | B22: Water/sewer/trash | C22: All utilities plus basic cable and Wi-Fi | D22: All utilities plus phone, premium cable; taxes/insurance where applicable
A23: Transportation | B23: Scheduled group only | C23: Plus scheduled medical within 10 miles; posted rates beyond | D23: Plus personal on-demand trip allowance and airport runs
A24: Wellness & safety | B24: Emergency pendant; fitness access | C24: Plus monthly clinic; daily check-in option; campus-wide mobile pendant | D24: Plus wellness allowance, health-center days, navigator; 24-hr security / gated
A25: Convenience | B25: Business-hours front desk; short price list | C25: Published Base + Choice menu; second-person fee | D25: 24/7 concierge; monthly convenience credit; cottage services coordinator
A26: Target buyer (per Saxman / Witzgall) | B26: Most independent, price-sensitive downsizer who wants to stop mowing | C26: Mainstream active adult who wants choices without a care-driven decision | D26: Buyer trading up from a CCRC villa or luxury rental who expects everything handled
A27: Closest benchmarks in the data | B27: Highgrove at Tates Creek; Village at Bay Ridge; Swanhaven Manor; Integrated Senior Living (TX); Tabor Hills; Vitalia rentals | C27: Witzgall rental profile; Hamilton Trace; Cedarhurst of Frankfort; Woodland Terrace; Cedarbrook of Northville; Provincial/Discovery IL | D27: Smith Crossing; Five Star Residences; The Stratford; Twin Lakes; Lake Forest Place; Concordia Life Plan (OKC); Zarrow Pointe

Sheet Sources & Method
A1: Sources, attribution and method notes
A3: Source (Person) | B3: Document | C3: Date | D3: What it contributes | E3: Rows in Consolidated Data | F3: Caveats
A4: Laura Lopez | B4: Word doc: Villa Study Scratch List (Updated Oct 2023) | C4: Oct 2023 (doc); received by email Sept 2026 | D4: Community-by-community inventory of villa/cottage products: operator, location, type, count, pricing, included amenities, sub-market. | E4: =COUNTIF('Consolidated Data'!$B$2:$B$231,"Laura Lopez") -> 215 | F4: Web-researched Oct 2023; "Not stated" means not found online, not necessarily absent. Several entries flagged "none confirmed."
A5: Ken Witzgall | B5: PDF: Senior Living Cottages & Independent Villas: The Rental Model (Curated, AI location-intelligence report) | C5: Generated Sept 15, 2026 | D5: Industry profile of the rental cottage model: included vs. ancillary services by function, fee structure, strategic takeaways. | E5: =COUNTIF('Consolidated Data'!$B$2:$B$231,"Ken Witzgall") -> 2 | F5: AI-generated (Curated platform) from web sources dated Sept 15, 2026; price ranges are indicative national norms.
A6: Scott Wood | B6: Email: service comparison table (Provincial/Discovery IL vs Integrated Senior Living TX) | C6: Email, Sept 2026 | D6: Service package at two operators (transportation, life enrichment, culinary, housekeeping, wellness, other). | E6: =COUNTIF('Consolidated Data'!$B$2:$B$231,"Scott Wood") -> 2 | F6: No dates, prices, or detail on maintenance/utilities/safety; "N/A" reported for wellness and other services.
A7: Jennifer Saxman | B7: Email: detached cottage / villa benchmarking table and narrative | C7: Email, Sept 2026 | D7: Benchmark table of 6 detached-home products across 9 service functions, 4 narrative examples, and a Base + Choice recommendation. | E7: =COUNTIF('Consolidated Data'!$B$2:$B$231,"Jennifer Saxman") -> 11 | F7: Operators, locations and prices mostly not stated; narrative examples are qualitative.
A9: Method
A10: • Every amenity line in the Lopez document was mapped to one or more of the nine service functions used in Jennifer Saxman's table (plus a Residence Features column for garages, washer/dryers, patios, etc.) using keyword rules; the original wording is preserved in each cell.
A11: • Campus-amenity lists (e.g., "Campus amenities (pool; gym; chapel)") are placed under Life Enrichment; when they mention fitness, pool, wellness, therapy or clinic they are also echoed under Wellness with a "(via campus amenities)" prefix.
A12: • Tier columns (Included / Included (limited) / Available (extra cost) / Not provided / Not stated) are derived from the text: wording such as "available," "optional," "extra," "credit," "allowance," "separately" or a dollar rate is classed as Available (extra cost).
A13: • Monthly Fee Low/High are parsed from the reported pricing text: dollar figures under $10,000 on the monthly side of the text, excluding entry/entrance fees, deposits and community fees. Entry fees are kept as text in the pricing column.
A14: • Witzgall's model is represented as two rows (typical included package; typical ancillary menu) because it is not a community-level inventory. Wood's table becomes two operator rows. Saxman's six-community table becomes six rows, her narrative examples four rows, and her overall takeaway one row.
A15: • Synthesis counts use COUNTIFS formulas over the tier columns and recalculate if rows are edited. Lopez pricing statistics reference the contiguous Lopez block (rows 2–216).
A16: • Recommendations are analytical judgments built from the synthesis; the Good/Better/Best price bands in the Packaging row are a planning assumption mapped onto Witzgall's $2,500–$6,500+ range, not sourced pricing.
A17: • Workbook built Sept 17, 2026 from the four sources above.
